{"SubTexture":[{"y":0,"width":101,"height":85,"name":"dandelion.png","x":0},{"y":87,"width":75,"height":63,"name":"dandelion","x":0},{"y":39,"width":11,"height":15,"name":"legRight","x":115},{"y":27,"width":17,"height":10,"name":"tail","x":103},{"y":56,"width":9,"height":17,"name":"handRight","x":115},{"y":0,"width":17,"height":25,"name":"body","x":103},{"y":58,"width":10,"height":15,"name":"legLeft","x":103},{"y":39,"width":10,"height":17,"name":"handLeft","x":103},{"y":87,"width":35,"height":46,"name":"head","x":77},{"y":75,"width":6,"height":5,"name":"lips","x":103},{"y":75,"width":14,"height":5,"name":"eyes","x":111},{"y":135,"width":32,"height":11,"name":"viyi","x":77}],"name":"dandelion","imagePath":"texture.png"}