{"armature":[{"animation":[{"fadeInTime":0,"loop":1,"name":"close","timeline":[{"name":"cep","scale":1,"frame":[{"z":1,"duration":1,"transform":{"y":13.13,"skX":0,"pX":0,"scX":1,"skY":0,"pY":0,"scY":1.06,"x":8.88}}],"offset":0},{"name":"osnova_t","scale":1,"frame":[{"z":15,"duration":1,"transform":{"y":0.2,"skX":0,"pX":0,"scX":1,"skY":0,"pY":0,"scY":1,"x":-0.2}}],"offset":0}],"tweenEasing":null,"scale":1,"duration":1,"autoTween":1},{"fadeInTime":0,"loop":1,"name":"start","timeline":[{"name":"osnova","scale":1,"frame":[{"displayIndex":-1,"duration":14},{"z":0,"duration":10,"transform":{"y":0.2,"skX":0,"pX":0,"scX":1,"skY":0,"pY":0,"scY":1,"x":-0.2}}],"offset":0},{"name":"cep","scale":1,"frame":[{"z":1,"duration":166,"transform":{"y":13.13,"skX":0,"pX":0,"scX":1,"skY":0,"pY":0,"scY":1.06,"x":8.88}}],"offset":0},{"name":"legRight","scale":1,"frame":[{"z":3,"tweenEasing":1,"duration":2,"transform":{"y":3.05,"skX":0,"pX":0,"scX":-1,"skY":0,"pY":0,"scY":1,"x":10.98}},{"z":3,"tweenEasing":0,"duration":3,"transform":{"y":31.7,"skX":-45,"pX":0,"scX":-1,"skY":-45,"pY":0,"scY":1,"x":50.48}},{"z":3,"tweenEasing":0,"duration":3,"transform":{"y":39.67,"skX":21.41,"pX":0.03,"scX":-1,"skY":21.41,"pY":-0.02,"scY":1,"x":50.68}},{"z":3,"tweenEasing":0,"duration":3,"transform":{"y":40.42,"skX":68.03,"pX":0.03,"scX":-1,"skY":68.03,"pY":-0.07,"scY":1.3,"x":39.83}},{"z":3,"duration":1,"transform":{"y":45.2,"skX":21.41,"pX":0.05,"scX":-1,"skY":21.41,"pY":0,"scY":1,"x":57.9}},{"z":3,"tweenEasing":0,"duration":3,"transform":{"y":50.2,"skX":-68.03,"pX":0,"scX":1,"skY":-68.03,"pY":-0.07,"scY":1.3,"x":70.1}},{"z":3,"tweenEasing":0,"duration":8,"transform":{"y":54.25,"skX":-8.03,"pX":0,"scX":1,"skY":-8.03,"pY":-0.05,"scY":1.16,"x":39.83}},{"z":3,"duration":1,"transform":{"y":54.25,"skX":-8.03,"pX":0,"scX":1,"skY":-8.03,"pY":-0.05,"scY":1.16,"x":39.83}}],"offset":0},{"name":"tail","scale":1,"frame":[{"z":4,"tweenEasing":1,"duration":2,"transform":{"y":-13.35,"skX":60,"pX":0,"scX":-1,"skY":60,"pY":0,"scY":1,"x":2.58}},{"z":4,"tweenEasing":0,"duration":3,"transform":{"y":22.23,"skX":59.95,"pX":0,"scX":-1,"skY":59.95,"pY":0,"scY":1,"x":33.58}},{"z":4,"tweenEasing":0,"duration":3,"transform":{"y":23.85,"skX":59.94,"pX":0,"scX":-1,"skY":59.94,"pY":-0.02,"scY":1,"x":46.45}},{"z":4,"tweenEasing":0,"duration":3,"transform":{"y":30.4,"skX":59.95,"pX":0,"scX":-1,"skY":59.95,"pY":0,"scY":1,"x":47.65}},{"z":4,"duration":1,"transform":{"y":29.38,"skX":59.94,"pX":-0.02,"scX":-1,"skY":59.94,"pY":0,"scY":1,"x":53.68}},{"z":4,"tweenEasing":0,"duration":3,"transform":{"y":40.17,"skX":-59.95,"pX":0,"scX":1,"skY":-59.95,"pY":0,"scY":1,"x":62.28}},{"z":4,"tweenEasing":0,"duration":8,"transform":{"y":37.38,"skX":-59.95,"pX":0,"scX":1,"skY":-59.95,"pY":0,"scY":1,"x":44.98}},{"z":4,"duration":1,"transform":{"y":37.38,"skX":-59.95,"pX":0,"scX":1,"skY":-59.95,"pY":0,"scY":1,"x":44.98}}],"offset":0},{"name":"handRight","scale":1,"frame":[{"z":5,"tweenEasing":1,"duration":2,"transform":{"y":-29.3,"skX":-10.81,"pX":0,"scX":-1,"skY":-10.81,"pY":0,"scY":1.17,"x":11.18}},{"z":5,"tweenEasing":0,"duration":3,"transform":{"y":6.33,"skX":49.23,"pX":-0.02,"scX":-1,"skY":49.23,"pY":-0.05,"scY":1.17,"x":42.15}},{"z":5,"tweenEasing":0,"duration":3,"transform":{"y":11.53,"skX":10.62,"pX":-0.02,"scX":-1,"skY":10.62,"pY":-0.02,"scY":1.17,"x":55.08}},{"z":5,"tweenEasing":0,"duration":3,"transform":{"y":20.02,"skX":-40.77,"pX":-0.02,"scX":-1,"skY":-40.77,"pY":-0.05,"scY":1.17,"x":53.53}},{"z":5,"duration":1,"transform":{"y":17.05,"skX":10.62,"pX":-0.02,"scX":-1,"skY":10.62,"pY":0.03,"scY":1.17,"x":62.3}},{"z":5,"tweenEasing":0,"duration":3,"transform":{"y":29.8,"skX":40.77,"pX":-0.05,"scX":1,"skY":40.77,"pY":-0.02,"scY":1.17,"x":56.4}},{"z":5,"tweenEasing":0,"duration":8,"transform":{"y":24.5,"skX":-4.23,"pX":-0.05,"scX":1,"skY":-4.23,"pY":-0.02,"scY":1.17,"x":36.65}},{"z":5,"duration":1,"transform":{"y":24.5,"skX":-4.23,"pX":-0.05,"scX":1,"skY":-4.23,"pY":-0.02,"scY":1.17,"x":36.65}}],"offset":0},{"name":"body","scale":1,"frame":[{"z":6,"tweenEasing":1,"duration":2,"transform":{"y":-7.95,"skX":4.19,"pX":0,"scX":-1,"skY":4.19,"pY":0,"scY":0.93,"x":5.35}},{"z":6,"tweenEasing":0,"duration":3,"transform":{"y":27.63,"skX":4.05,"pX":0,"scX":-1,"skY":4.05,"pY":0,"scY":0.93,"x":36.33}},{"z":6,"tweenEasing":0,"duration":3,"transform":{"y":29.28,"skX":4.02,"pX":0,"scX":-1,"skY":4.02,"pY":0,"scY":0.93,"x":49.18}},{"z":6,"tweenEasing":0,"duration":3,"transform":{"y":35.8,"skX":4.05,"pX":0,"scX":-1,"skY":4.05,"pY":0,"scY":0.93,"x":50.4}},{"z":6,"duration":1,"transform":{"y":34.8,"skX":4.02,"pX":0,"scX":-1,"skY":4.02,"pY":0,"scY":0.93,"x":56.4}},{"z":6,"tweenEasing":0,"duration":3,"transform":{"y":45.58,"skX":-4.05,"pX":0,"scX":1,"skY":-4.05,"pY":0,"scY":0.93,"x":59.53}},{"z":6,"tweenEasing":0,"duration":8,"transform":{"y":42.78,"skX":-4.05,"pX":0,"scX":1,"skY":-4.05,"pY":0,"scY":0.93,"x":42.23}},{"z":6,"duration":1,"transform":{"y":42.78,"skX":-4.05,"pX":0,"scX":1,"skY":-4.05,"pY":0,"scY":0.93,"x":42.23}}],"offset":0},{"name":"legLeft","scale":1,"frame":[{"z":7,"tweenEasing":1,"duration":2,"transform":{"y":4.3,"skX":0,"pX":0,"scX":-1,"skY":0,"pY":0,"scY":1,"x":0.73}},{"z":7,"tweenEasing":0,"duration":3,"transform":{"y":32.78,"skX":45,"pX":0.03,"scX":-1,"skY":45,"pY":-0.02,"scY":1,"x":22.9}},{"z":7,"tweenEasing":0,"duration":3,"transform":{"y":40.38,"skX":-6.41,"pX":-0.02,"scX":-1,"skY":-6.41,"pY":-0.02,"scY":1,"x":47.25}},{"z":7,"tweenEasing":0,"duration":3,"transform":{"y":43.9,"skX":-45,"pX":0,"scX":-1,"skY":-45,"pY":0,"scY":1.21,"x":57.83}},{"z":7,"duration":1,"transform":{"y":45.9,"skX":-6.41,"pX":0.03,"scX":-1,"skY":-6.41,"pY":-0.05,"scY":1,"x":54.48}},{"z":7,"tweenEasing":0,"duration":3,"transform":{"y":53.68,"skX":45,"pX":-0.02,"scX":1,"skY":45,"pY":0,"scY":1.21,"x":52.1}},{"z":7,"tweenEasing":0,"duration":8,"transform":{"y":56.33,"skX":0,"pX":0,"scX":1,"skY":0,"pY":0,"scY":1.21,"x":46}},{"z":7,"duration":1,"transform":{"y":56.33,"skX":0,"pX":0,"scX":1,"skY":0,"pY":0,"scY":1.21,"x":46}}],"offset":0},{"name":"head","scale":1,"frame":[{"z":8,"tweenEasing":1,"duration":2,"transform":{"y":-26.55,"skX":-0.02,"pX":0,"scX":-1,"skY":-0.02,"pY":0,"scY":1,"x":7.88}},{"z":8,"tweenEasing":0,"duration":3,"transform":{"y":9.03,"skX":-0.01,"pX":0,"scX":-1,"skY":-0.01,"pY":0,"scY":1,"x":38.85}},{"z":8,"tweenEasing":0,"duration":3,"transform":{"y":10.65,"skX":0,"pX":0,"scX":-1,"skY":0,"pY":0,"scY":1,"x":51.73}},{"z":8,"tweenEasing":0,"duration":3,"transform":{"y":17.2,"skX":-0.01,"pX":0,"scX":-1,"skY":-0.01,"pY":0,"scY":1,"x":52.93}},{"z":8,"duration":1,"transform":{"y":16.18,"skX":0,"pX":0,"scX":-1,"skY":0,"pY":0,"scY":1,"x":58.95}},{"z":8,"tweenEasing":0,"duration":3,"transform":{"y":26.98,"skX":0.01,"pX":0,"scX":1,"skY":0.01,"pY":0,"scY":1,"x":57}},{"z":8,"tweenEasing":0,"duration":8,"transform":{"y":24.18,"skX":0.01,"pX":0,"scX":1,"skY":0.01,"pY":0,"scY":1,"x":39.7}},{"z":8,"duration":1,"transform":{"y":24.18,"skX":0.01,"pX":0,"scX":1,"skY":0.01,"pY":0,"scY":1,"x":39.7}}],"offset":0},{"name":"eye","scale":1,"frame":[{"z":10,"duration":1,"transform":{"y":-43.27,"skX":-1.26,"pX":0,"scX":-1.02,"skY":5.19,"pY":0,"scY":1.44,"x":15.33}},{"z":10,"duration":1,"transform":{"y":-15.95,"skX":-1.25,"pX":0,"scX":-1.01,"skY":5.03,"pY":-0.05,"scY":1.44,"x":38.73}},{"z":10,"tweenEasing":0,"duration":3,"transform":{"y":-7.7,"skX":-1.25,"pX":0,"scX":-1.01,"skY":5.05,"pY":-0.02,"scY":1.44,"x":46.3}},{"z":10,"tweenEasing":0,"duration":3,"transform":{"y":-6.05,"skX":-1.25,"pX":-0.02,"scX":-1.01,"skY":5.02,"pY":0,"scY":1.44,"x":59.15}},{"z":10,"tweenEasing":0,"duration":3,"transform":{"y":0.48,"skX":-1.25,"pX":0,"scX":-1.01,"skY":5.05,"pY":0,"scY":1.44,"x":60.38}},{"z":10,"duration":1,"transform":{"y":-0.52,"skX":-1.25,"pX":-0.02,"scX":-1.01,"skY":5.02,"pY":0,"scY":1.44,"x":66.38}},{"z":10,"tweenEasing":0,"duration":3,"transform":{"y":10.25,"skX":1.25,"pX":0,"scX":1.01,"skY":-5.05,"pY":0,"scY":1.44,"x":49.55}},{"z":10,"tweenEasing":0,"duration":8,"transform":{"y":7.45,"skX":1.25,"pX":0,"scX":1.01,"skY":-5.05,"pY":-0.02,"scY":1.44,"x":32.25}},{"z":10,"duration":1,"transform":{"y":7.45,"skX":1.25,"pX":0,"scX":1.01,"skY":-5.05,"pY":-0.02,"scY":1.44,"x":32.25}}],"offset":0},{"name":"viyi","scale":1,"frame":[{"z":11,"duration":1,"transform":{"y":-54.77,"skX":0.98,"pX":0,"scX":-1,"skY":-1.4,"pY":0,"scY":1,"x":13.43}},{"z":11,"duration":1,"transform":{"y":-27.47,"skX":0.79,"pX":0,"scX":-1,"skY":-1.27,"pY":0,"scY":1,"x":36.8}},{"z":11,"tweenEasing":0,"duration":3,"transform":{"y":-19.2,"skX":0.81,"pX":0,"scX":-1,"skY":-1.29,"pY":0,"scY":1,"x":44.38}},{"z":11,"tweenEasing":0,"duration":3,"transform":{"y":-17.55,"skX":0.77,"pX":0,"scX":-1,"skY":-1.26,"pY":-0.02,"scY":1,"x":57.23}},{"z":11,"tweenEasing":0,"duration":3,"transform":{"y":-11.02,"skX":0.81,"pX":0,"scX":-1,"skY":-1.29,"pY":0,"scY":1,"x":58.45}},{"z":11,"duration":1,"transform":{"y":-12.02,"skX":0.77,"pX":0,"scX":-1,"skY":-1.26,"pY":0,"scY":1,"x":64.45}},{"z":11,"tweenEasing":0,"duration":3,"transform":{"y":-1.25,"skX":-0.81,"pX":0,"scX":1,"skY":1.29,"pY":0,"scY":1,"x":51.48}},{"z":11,"tweenEasing":0,"duration":8,"transform":{"y":-4.05,"skX":-0.81,"pX":0,"scX":1,"skY":1.29,"pY":0,"scY":1,"x":34.17}},{"z":11,"duration":1,"transform":{"y":-4.05,"skX":-0.81,"pX":0,"scX":1,"skY":1.29,"pY":0,"scY":1,"x":34.17}}],"offset":0},{"name":"handLeft","scale":1,"frame":[{"z":12,"tweenEasing":1,"duration":2,"transform":{"y":-23.9,"skX":-29.8,"pX":0,"scX":-1,"skY":-29.8,"pY":0,"scY":0.92,"x":1.9}},{"z":12,"tweenEasing":0,"duration":3,"transform":{"y":11.7,"skX":-74.81,"pX":0.03,"scX":-1,"skY":-74.81,"pY":-0.05,"scY":0.92,"x":32.88}},{"z":12,"tweenEasing":0,"duration":3,"transform":{"y":13.28,"skX":-23.44,"pX":0.03,"scX":-1,"skY":-23.45,"pY":-0.07,"scY":0.92,"x":45.73}},{"z":12,"tweenEasing":0,"duration":3,"transform":{"y":19.88,"skX":60.19,"pX":0.03,"scX":-1,"skY":60.19,"pY":-0.05,"scY":0.92,"x":46.95}},{"z":12,"duration":1,"transform":{"y":18.8,"skX":-23.44,"pX":0.03,"scX":-1,"skY":-23.45,"pY":-0.07,"scY":0.92,"x":52.95}},{"z":12,"tweenEasing":0,"duration":3,"transform":{"y":29.65,"skX":-60.19,"pX":0.03,"scX":1,"skY":-60.19,"pY":-0.07,"scY":0.92,"x":62.98}},{"z":12,"tweenEasing":0,"duration":8,"transform":{"y":26.85,"skX":14.81,"pX":0.03,"scX":1,"skY":14.81,"pY":-0.07,"scY":0.92,"x":45.7}},{"z":12,"duration":1,"transform":{"y":26.85,"skX":14.81,"pX":0.03,"scX":1,"skY":14.81,"pY":-0.07,"scY":0.92,"x":45.7}}],"offset":0},{"name":"osnova_t","scale":1,"frame":[{"z":15,"duration":14,"transform":{"y":0.2,"skX":0,"pX":0,"scX":1,"skY":0,"pY":0,"scY":1,"x":-0.2}},{"displayIndex":-1,"duration":10}],"offset":0}],"tweenEasing":null,"scale":1,"duration":24,"autoTween":0},{"fadeInTime":0,"loop":1,"name":"idle_1","timeline":[{"name":"osnova","scale":1,"frame":[{"z":0,"duration":263,"transform":{"y":0.2,"skX":0,"pX":0,"scX":1,"skY":0,"pY":0,"scY":1,"x":-0.2}}],"offset":0},{"name":"cep","scale":1,"frame":[{"z":1,"duration":142,"transform":{"y":13.13,"skX":0,"pX":0,"scX":1,"skY":0,"pY":0,"scY":1.06,"x":8.88}}],"offset":0},{"name":"legRight","scale":1,"frame":[{"z":3,"tweenEasing":0,"duration":5,"transform":{"y":54.25,"skX":-8.03,"pX":0,"scX":1,"skY":-8.03,"pY":-0.05,"scY":1.16,"x":39.83}},{"z":3,"tweenEasing":0,"duration":7,"transform":{"y":54.28,"skX":-8.01,"pX":0.03,"scX":1,"skY":-8.01,"pY":-0.07,"scY":1.16,"x":39.83}},{"z":3,"tweenEasing":0,"duration":27,"transform":{"y":54.25,"skX":-8.03,"pX":0,"scX":1,"skY":-8.03,"pY":-0.05,"scY":1.16,"x":39.83}},{"z":3,"tweenEasing":0,"duration":4,"transform":{"y":54.25,"skX":-8.03,"pX":0,"scX":1,"skY":-8.03,"pY":-0.05,"scY":1.16,"x":39.83}},{"z":3,"tweenEasing":0,"duration":6,"transform":{"y":54.25,"skX":-8.03,"pX":0,"scX":1,"skY":-8.03,"pY":-0.05,"scY":1.16,"x":39.83}},{"z":3,"tweenEasing":0,"duration":5,"transform":{"y":54.25,"skX":-8.03,"pX":0,"scX":1,"skY":-8.03,"pY":-0.05,"scY":1.16,"x":39.83}},{"z":3,"tweenEasing":0,"duration":5,"transform":{"y":54.25,"skX":-8.03,"pX":0,"scX":1,"skY":-8.03,"pY":-0.05,"scY":1.16,"x":39.83}},{"z":3,"tweenEasing":0,"duration":4,"transform":{"y":54.25,"skX":-8.03,"pX":0,"scX":1,"skY":-8.03,"pY":-0.05,"scY":1.16,"x":39.83}},{"z":3,"tweenEasing":0,"duration":25,"transform":{"y":54.25,"skX":-8.03,"pX":-0.02,"scX":1,"skY":-8.03,"pY":-0.1,"scY":1.35,"x":39.85}},{"z":3,"tweenEasing":0,"duration":9,"transform":{"y":54.25,"skX":-8.03,"pX":-0.02,"scX":1,"skY":-8.03,"pY":-0.1,"scY":1.35,"x":39.85}},{"z":3,"duration":1,"transform":{"y":54.25,"skX":-8.03,"pX":0,"scX":1,"skY":-8.03,"pY":-0.05,"scY":1.16,"x":39.83}}],"offset":0},{"name":"tail","scale":1,"frame":[{"z":4,"tweenEasing":0,"duration":5,"transform":{"y":37.38,"skX":-59.95,"pX":0,"scX":1,"skY":-59.95,"pY":0,"scY":1,"x":44.98}},{"z":4,"tweenEasing":0,"duration":7,"transform":{"y":37.95,"skX":-55.45,"pX":-0.05,"scX":1,"skY":-55.45,"pY":0,"scY":1,"x":45.35}},{"z":4,"tweenEasing":0,"duration":27,"transform":{"y":37.38,"skX":-59.95,"pX":0,"scX":1,"skY":-59.95,"pY":0,"scY":1,"x":44.98}},{"z":4,"tweenEasing":0,"duration":4,"transform":{"y":37.38,"skX":-59.95,"pX":0,"scX":1,"skY":-59.95,"pY":0,"scY":1,"x":44.98}},{"z":4,"tweenEasing":0,"duration":6,"transform":{"y":37.38,"skX":-59.95,"pX":0,"scX":1,"skY":-59.95,"pY":0,"scY":1,"x":44.98}},{"z":4,"tweenEasing":0,"duration":5,"transform":{"y":38.8,"skX":-44.95,"pX":0,"scX":1,"skY":-44.95,"pY":0,"scY":1,"x":46.23}},{"z":4,"tweenEasing":0,"duration":5,"transform":{"y":34.4,"skX":-80.44,"pX":0.03,"scX":1,"skY":-80.44,"pY":0,"scY":1,"x":44}},{"z":4,"tweenEasing":0,"duration":4,"transform":{"y":34.4,"skX":-80.44,"pX":0.03,"scX":1,"skY":-80.44,"pY":0,"scY":1,"x":44}},{"z":4,"tweenEasing":0,"duration":25,"transform":{"y":31.6,"skX":-80.44,"pX":0,"scX":1,"skY":-80.44,"pY":0,"scY":1,"x":43.4}},{"z":4,"tweenEasing":0,"duration":9,"transform":{"y":31.6,"skX":-80.44,"pX":0,"scX":1,"skY":-80.44,"pY":0,"scY":1,"x":43.4}},{"z":4,"duration":1,"transform":{"y":37.38,"skX":-59.95,"pX":0,"scX":1,"skY":-59.95,"pY":0,"scY":1,"x":44.98}}],"offset":0},{"name":"handRight","scale":1,"frame":[{"z":5,"tweenEasing":0,"duration":5,"transform":{"y":24.5,"skX":-4.23,"pX":-0.05,"scX":1,"skY":-4.23,"pY":-0.02,"scY":1.17,"x":36.65}},{"z":5,"tweenEasing":0,"duration":7,"transform":{"y":24.48,"skX":-7.09,"pX":-0.07,"scX":1,"skY":-7.09,"pY":-0.1,"scY":0.87,"x":38.05}},{"z":5,"tweenEasing":0,"duration":27,"transform":{"y":24.5,"skX":40.77,"pX":-0.05,"scX":1,"skY":40.77,"pY":-0.02,"scY":1.17,"x":36.67}},{"z":5,"tweenEasing":0,"duration":4,"transform":{"y":24.5,"skX":40.77,"pX":-0.05,"scX":1,"skY":40.77,"pY":-0.02,"scY":1.17,"x":36.67}},{"z":5,"tweenEasing":0,"duration":6,"transform":{"y":24.53,"skX":25.77,"pX":-0.05,"scX":1,"skY":25.77,"pY":-0.07,"scY":1.17,"x":36.67}},{"z":5,"tweenEasing":0,"duration":5,"transform":{"y":24.2,"skX":145.77,"pX":-0.05,"scX":1,"skY":145.77,"pY":-0.02,"scY":1.17,"x":41.5}},{"z":5,"tweenEasing":0,"duration":5,"transform":{"y":25.23,"skX":110.28,"pX":0.03,"scX":1,"skY":110.28,"pY":0,"scY":1.17,"x":31.7}},{"z":5,"tweenEasing":0,"duration":4,"transform":{"y":24.43,"skX":103.23,"pX":-0.05,"scX":1,"skY":103.23,"pY":-0.02,"scY":1.17,"x":37.5}},{"z":5,"tweenEasing":0,"duration":25,"transform":{"y":21.63,"skX":65.28,"pX":-0.02,"scX":1,"skY":65.28,"pY":-0.02,"scY":1.17,"x":36.9}},{"z":5,"tweenEasing":0,"duration":9,"transform":{"y":21.63,"skX":65.28,"pX":-0.02,"scX":1,"skY":65.28,"pY":-0.02,"scY":1.17,"x":36.9}},{"z":5,"duration":1,"transform":{"y":24.5,"skX":-4.23,"pX":-0.05,"scX":1,"skY":-4.23,"pY":-0.02,"scY":1.17,"x":36.65}}],"offset":0},{"name":"body","scale":1,"frame":[{"z":6,"tweenEasing":0,"duration":5,"transform":{"y":42.78,"skX":-4.05,"pX":0,"scX":1,"skY":-4.05,"pY":0,"scY":0.93,"x":42.23}},{"z":6,"tweenEasing":0,"duration":7,"transform":{"y":43.13,"skX":0.47,"pX":0,"scX":1,"skY":0.47,"pY":0,"scY":0.93,"x":42.18}},{"z":6,"tweenEasing":0,"duration":27,"transform":{"y":42.78,"skX":-4.05,"pX":0,"scX":1,"skY":-4.05,"pY":0,"scY":0.93,"x":42.23}},{"z":6,"tweenEasing":0,"duration":4,"transform":{"y":42.78,"skX":-4.05,"pX":0,"scX":1,"skY":-4.05,"pY":0,"scY":0.93,"x":42.23}},{"z":6,"tweenEasing":0,"duration":3,"transform":{"y":42.78,"skX":-4.05,"pX":0,"scX":1,"skY":-4.05,"pY":0,"scY":0.93,"x":42.23}},{"z":6,"tweenEasing":0,"duration":3,"transform":{"y":43.05,"skX":3.3,"pX":0,"scX":1,"skY":3.3,"pY":0,"scY":0.93,"x":42.2}},{"z":6,"tweenEasing":0,"duration":5,"transform":{"y":43.3,"skX":10.95,"pX":0,"scX":1,"skY":10.95,"pY":0,"scY":0.93,"x":42.15}},{"z":6,"tweenEasing":0,"duration":5,"transform":{"y":40.4,"skX":-24.54,"pX":0,"scX":1,"skY":-24.54,"pY":0,"scY":0.93,"x":43.33}},{"z":6,"tweenEasing":0,"duration":4,"transform":{"y":40.4,"skX":-24.54,"pX":0,"scX":1,"skY":-24.54,"pY":0,"scY":0.93,"x":43.33}},{"z":6,"tweenEasing":0,"duration":25,"transform":{"y":37.6,"skX":-24.54,"pX":0,"scX":1,"skY":-24.54,"pY":0,"scY":0.93,"x":42.73}},{"z":6,"tweenEasing":0,"duration":9,"transform":{"y":37.6,"skX":-24.54,"pX":0,"scX":1,"skY":-24.54,"pY":0,"scY":0.93,"x":42.73}},{"z":6,"duration":1,"transform":{"y":42.78,"skX":-4.05,"pX":0,"scX":1,"skY":-4.05,"pY":0,"scY":0.93,"x":42.23}}],"offset":0},{"name":"legLeft","scale":1,"frame":[{"z":7,"tweenEasing":0,"duration":5,"transform":{"y":56.33,"skX":0,"pX":0,"scX":1,"skY":0,"pY":0,"scY":1.21,"x":46}},{"z":7,"tweenEasing":0,"duration":7,"transform":{"y":56.33,"skX":0,"pX":0,"scX":1,"skY":0,"pY":0,"scY":1.21,"x":46}},{"z":7,"tweenEasing":0,"duration":27,"transform":{"y":56.33,"skX":0,"pX":0,"scX":1,"skY":0,"pY":0,"scY":1.21,"x":46}},{"z":7,"tweenEasing":0,"duration":4,"transform":{"y":56.33,"skX":0,"pX":0,"scX":1,"skY":0,"pY":0,"scY":1.21,"x":46}},{"z":7,"tweenEasing":0,"duration":6,"transform":{"y":56.33,"skX":0,"pX":0,"scX":1,"skY":0,"pY":0,"scY":1.21,"x":46}},{"z":7,"tweenEasing":0,"duration":5,"transform":{"y":56.33,"skX":0,"pX":0,"scX":1,"skY":0,"pY":0,"scY":1.21,"x":46}},{"z":7,"tweenEasing":0,"duration":5,"transform":{"y":56.33,"skX":0,"pX":0,"scX":1,"skY":0,"pY":0,"scY":1.21,"x":46}},{"z":7,"tweenEasing":0,"duration":4,"transform":{"y":56.33,"skX":0,"pX":0,"scX":1,"skY":0,"pY":0,"scY":1.21,"x":46}},{"z":7,"tweenEasing":0,"duration":25,"transform":{"y":56.3,"skX":0,"pX":0,"scX":1,"skY":0,"pY":0,"scY":1.62,"x":46}},{"z":7,"tweenEasing":0,"duration":9,"transform":{"y":56.3,"skX":0,"pX":0,"scX":1,"skY":0,"pY":0,"scY":1.62,"x":46}},{"z":7,"duration":1,"transform":{"y":56.33,"skX":0,"pX":0,"scX":1,"skY":0,"pY":0,"scY":1.21,"x":46}}],"offset":0},{"name":"head","scale":1,"frame":[{"z":8,"tweenEasing":0,"duration":5,"transform":{"y":24.18,"skX":0.01,"pX":0,"scX":1,"skY":0.01,"pY":0,"scY":1,"x":39.7}},{"z":8,"tweenEasing":0,"duration":7,"transform":{"y":24.75,"skX":11.95,"pX":0,"scX":1,"skY":11.95,"pY":0,"scY":1,"x":41.08}},{"z":8,"tweenEasing":0,"duration":27,"transform":{"y":24.18,"skX":-14.99,"pX":0,"scX":1,"skY":-14.99,"pY":0,"scY":1,"x":39.7}},{"z":8,"tweenEasing":0,"duration":4,"transform":{"y":24.18,"skX":-14.99,"pX":0,"scX":1,"skY":-14.99,"pY":0,"scY":1,"x":39.7}},{"z":8,"tweenEasing":0,"duration":6,"transform":{"y":24.18,"skX":0.01,"pX":0,"scX":1,"skY":0.01,"pY":0,"scY":1,"x":39.7}},{"z":8,"tweenEasing":0,"duration":5,"transform":{"y":24.68,"skX":47.73,"pX":0,"scX":1,"skY":47.73,"pY":0,"scY":1,"x":44.55}},{"z":8,"tweenEasing":0,"duration":5,"transform":{"y":25.08,"skX":-6.48,"pX":0,"scX":1,"skY":-6.48,"pY":0,"scY":1,"x":35.13}},{"z":8,"tweenEasing":0,"duration":4,"transform":{"y":25.08,"skX":-6.48,"pX":0,"scX":1,"skY":-6.48,"pY":0,"scY":1,"x":35.13}},{"z":8,"tweenEasing":0,"duration":25,"transform":{"y":23.43,"skX":-21.48,"pX":0,"scX":1,"skY":-21.48,"pY":0,"scY":1,"x":35.08}},{"z":8,"tweenEasing":0,"duration":9,"transform":{"y":23.43,"skX":-21.48,"pX":0,"scX":1,"skY":-21.48,"pY":0,"scY":1,"x":35.08}},{"z":8,"duration":1,"transform":{"y":24.18,"skX":0.01,"pX":0,"scX":1,"skY":0.01,"pY":0,"scY":1,"x":39.7}}],"offset":0},{"name":"eye","scale":1,"frame":[{"z":10,"tweenEasing":0,"duration":5,"transform":{"y":7.45,"skX":1.25,"pX":0,"scX":1.01,"skY":-5.05,"pY":-0.02,"scY":1.44,"x":32.25}},{"z":10,"tweenEasing":0,"duration":7,"transform":{"y":6.88,"skX":13.2,"pX":0,"scX":1.01,"skY":6.93,"pY":0,"scY":1.44,"x":37.3}},{"z":10,"tweenEasing":0,"duration":3,"transform":{"y":9.93,"skX":-13.75,"pX":0,"scX":1.01,"skY":-20.05,"pY":0,"scY":1.44,"x":28.18}},{"z":10,"tweenEasing":0,"duration":3,"transform":{"y":11.98,"skX":-13.57,"pX":0.03,"scX":1.01,"skY":-20.04,"pY":0,"scY":0.72,"x":28.2}},{"z":10,"tweenEasing":0,"duration":17,"transform":{"y":9.95,"skX":-13.54,"pX":0.03,"scX":1.01,"skY":-20.03,"pY":-0.02,"scY":1.43,"x":28.23}},{"z":10,"tweenEasing":0,"duration":2,"transform":{"y":9.95,"skX":-13.54,"pX":0.03,"scX":1.01,"skY":-20.03,"pY":-0.02,"scY":1.43,"x":28.23}},{"z":10,"tweenEasing":0,"duration":2,"transform":{"y":11.98,"skX":-13.57,"pX":0.03,"scX":1.01,"skY":-20.04,"pY":0,"scY":0.72,"x":28.2}},{"z":10,"tweenEasing":0,"duration":4,"transform":{"y":9.93,"skX":-13.75,"pX":0,"scX":1.01,"skY":-20.05,"pY":0,"scY":1.44,"x":28.18}},{"z":10,"tweenEasing":0,"duration":6,"transform":{"y":7.45,"skX":1.25,"pX":0,"scX":1.01,"skY":-5.05,"pY":-0.02,"scY":1.44,"x":32.25}},{"z":10,"tweenEasing":0,"duration":5,"transform":{"y":7.93,"skX":48.98,"pX":0,"scX":1.01,"skY":42.68,"pY":-0.02,"scY":1.44,"x":54.4}},{"z":10,"tweenEasing":0,"duration":5,"transform":{"y":9.35,"skX":-5.23,"pX":0,"scX":1.01,"skY":-11.53,"pY":-0.02,"scY":1.44,"x":24.63}},{"z":10,"tweenEasing":0,"duration":4,"transform":{"y":9.35,"skX":-5.23,"pX":0,"scX":1.01,"skY":-11.53,"pY":-0.02,"scY":1.44,"x":24.63}},{"z":10,"tweenEasing":0,"duration":2,"transform":{"y":10.93,"skX":-20.23,"pX":-0.02,"scX":1.01,"skY":-26.53,"pY":0.03,"scY":1.44,"x":20.85}},{"z":10,"tweenEasing":0,"duration":2,"transform":{"y":12.33,"skX":-20.08,"pX":-0.02,"scX":1.01,"skY":-26.55,"pY":0,"scY":0.49,"x":20.88}},{"z":10,"tweenEasing":0,"duration":21,"transform":{"y":10.95,"skX":-20.05,"pX":0,"scX":1.01,"skY":-26.55,"pY":-0.02,"scY":1.43,"x":20.83}},{"z":10,"tweenEasing":0,"duration":9,"transform":{"y":10.93,"skX":-20.23,"pX":-0.02,"scX":1.01,"skY":-26.53,"pY":0.03,"scY":1.44,"x":20.85}},{"z":10,"duration":1,"transform":{"y":7.45,"skX":1.25,"pX":0,"scX":1.01,"skY":-5.05,"pY":-0.02,"scY":1.44,"x":32.25}}],"offset":0},{"name":"viyi","scale":1,"frame":[{"z":11,"tweenEasing":0,"duration":5,"transform":{"y":-4.05,"skX":-0.81,"pX":0,"scX":1,"skY":1.29,"pY":0,"scY":1,"x":34.17}},{"z":11,"tweenEasing":0,"duration":7,"transform":{"y":-4.03,"skX":11.18,"pX":0,"scX":1,"skY":13.21,"pY":0.03,"scY":1,"x":41.55}},{"z":11,"tweenEasing":0,"duration":27,"transform":{"y":-1.65,"skX":-15.81,"pX":0,"scX":1,"skY":-13.71,"pY":0,"scY":1,"x":27.05}},{"z":11,"tweenEasing":0,"duration":4,"transform":{"y":-1.65,"skX":-15.81,"pX":0,"scX":1,"skY":-13.71,"pY":0,"scY":1,"x":27.05}},{"z":11,"tweenEasing":0,"duration":6,"transform":{"y":-4.05,"skX":-0.81,"pX":0,"scX":1,"skY":1.29,"pY":0,"scY":1,"x":34.17}},{"z":11,"tweenEasing":0,"duration":5,"transform":{"y":1.65,"skX":46.92,"pX":-0.02,"scX":1,"skY":49.01,"pY":-0.02,"scY":1,"x":61.7}},{"z":11,"tweenEasing":0,"duration":5,"transform":{"y":-2.35,"skX":-7.29,"pX":0.03,"scX":1,"skY":-5.19,"pY":0,"scY":1,"x":26.45}},{"z":11,"tweenEasing":0,"duration":4,"transform":{"y":-2.35,"skX":-7.29,"pX":0.03,"scX":1,"skY":-5.19,"pY":0,"scY":1,"x":26.45}},{"z":11,"tweenEasing":0,"duration":25,"transform":{"y":-0.82,"skX":-22.29,"pX":0,"scX":1,"skY":-20.19,"pY":0,"scY":1,"x":19.6}},{"z":11,"tweenEasing":0,"duration":9,"transform":{"y":-0.82,"skX":-22.29,"pX":0,"scX":1,"skY":-20.19,"pY":0,"scY":1,"x":19.6}},{"z":11,"duration":1,"transform":{"y":-4.05,"skX":-0.81,"pX":0,"scX":1,"skY":1.29,"pY":0,"scY":1,"x":34.17}}],"offset":0},{"name":"handLeft","scale":1,"frame":[{"z":12,"tweenEasing":0,"duration":5,"transform":{"y":26.85,"skX":14.81,"pX":0.03,"scX":1,"skY":14.81,"pY":-0.07,"scY":0.92,"x":45.7}},{"z":12,"tweenEasing":0,"duration":7,"transform":{"y":27.53,"skX":19.27,"pX":0.03,"scX":1,"skY":19.26,"pY":-0.07,"scY":0.92,"x":46.9}},{"z":12,"tweenEasing":0,"duration":27,"transform":{"y":26.85,"skX":14.81,"pX":0.03,"scX":1,"skY":14.81,"pY":-0.07,"scY":0.92,"x":45.7}},{"z":12,"tweenEasing":0,"duration":4,"transform":{"y":26.85,"skX":14.81,"pX":0.03,"scX":1,"skY":14.81,"pY":-0.07,"scY":0.92,"x":45.7}},{"z":12,"tweenEasing":0,"duration":6,"transform":{"y":26.85,"skX":14.81,"pX":0.03,"scX":1,"skY":14.81,"pY":-0.07,"scY":0.92,"x":45.7}},{"z":12,"tweenEasing":0,"duration":5,"transform":{"y":28.8,"skX":29.81,"pX":0.05,"scX":1,"skY":29.81,"pY":-0.05,"scY":0.92,"x":49.65}},{"z":12,"tweenEasing":0,"duration":5,"transform":{"y":24.33,"skX":-41.67,"pX":0.03,"scX":1,"skY":-41.66,"pY":-0.07,"scY":0.92,"x":41.05}},{"z":12,"tweenEasing":0,"duration":4,"transform":{"y":24.4,"skX":3.33,"pX":0,"scX":1,"skY":3.34,"pY":-0.1,"scY":0.92,"x":39.63}},{"z":12,"tweenEasing":0,"duration":25,"transform":{"y":21.6,"skX":93.33,"pX":0.03,"scX":1,"skY":93.34,"pY":-0.05,"scY":0.92,"x":39.03}},{"z":12,"tweenEasing":0,"duration":9,"transform":{"y":21.6,"skX":93.33,"pX":0.03,"scX":1,"skY":93.34,"pY":-0.05,"scY":0.92,"x":39.03}},{"z":12,"duration":1,"transform":{"y":26.85,"skX":14.81,"pX":0.03,"scX":1,"skY":14.81,"pY":-0.07,"scY":0.92,"x":45.7}}],"offset":0},{"name":"coin","scale":1,"frame":[{"displayIndex":-1,"duration":12},{"z":13,"tweenEasing":0,"duration":27,"transform":{"y":32.7,"skX":0,"pX":0,"scX":1,"skY":0,"pY":0,"scY":1,"x":23.83}},{"z":13,"tweenEasing":0,"duration":4,"transform":{"y":32.7,"skX":0,"pX":0,"scX":1,"skY":0,"pY":0,"scY":1,"x":23.83}},{"z":13,"tweenEasing":0,"duration":3,"transform":{"y":37.03,"skX":0,"pX":0,"scX":1,"skY":0,"pY":0,"scY":1,"x":27.85}},{"z":13,"tweenEasing":0,"duration":3,"transform":{"y":23.05,"skX":37.38,"pX":0,"scX":1,"skY":37.38,"pY":0.03,"scY":1,"x":24.13}},{"z":13,"tweenEasing":0,"duration":5,"transform":{"y":9.1,"skX":74.99,"pX":-0.02,"scX":1,"skY":74.99,"pY":0.03,"scY":1,"x":33.92}},{"z":13,"duration":1,"transform":{"y":23.73,"skX":150,"pX":0,"scX":1,"skY":150,"pY":0.03,"scY":1,"x":6.2}},{"displayIndex":-1,"duration":43}],"offset":0}],"tweenEasing":null,"scale":1,"duration":98,"autoTween":0},{"fadeInTime":0,"loop":1,"name":"idle_2","timeline":[{"name":"osnova","scale":1,"frame":[{"z":0,"duration":165,"transform":{"y":0.2,"skX":0,"pX":0,"scX":1,"skY":0,"pY":0,"scY":1,"x":-0.2}}],"offset":0},{"name":"cep","scale":1,"frame":[{"z":1,"duration":44,"transform":{"y":13.13,"skX":0,"pX":0,"scX":1,"skY":0,"pY":0,"scY":1.06,"x":8.88}},{"z":1,"duration":1,"transform":{"y":13.13,"skX":0,"pX":0,"scX":1,"skY":0,"pY":0,"scY":1.06,"x":8.88}},{"z":1,"duration":3,"transform":{"y":14,"skX":-30,"pX":0,"scX":1,"skY":-30,"pY":-0.02,"scY":1.06,"x":7.88}},{"z":1,"duration":3,"transform":{"y":13.13,"skX":-36.98,"pX":0,"scX":1,"skY":-36.98,"pY":0,"scY":1.06,"x":7.88}},{"z":1,"duration":3,"transform":{"y":14,"skX":-30,"pX":0,"scX":1,"skY":-30,"pY":-0.02,"scY":1.06,"x":7.88}},{"z":1,"duration":3,"transform":{"y":13.13,"skX":-36.98,"pX":0,"scX":1,"skY":-36.98,"pY":0,"scY":1.06,"x":7.88}},{"z":1,"duration":3,"transform":{"y":14,"skX":-30,"pX":0,"scX":1,"skY":-30,"pY":-0.02,"scY":1.06,"x":7.88}},{"z":1,"duration":3,"transform":{"y":13.13,"skX":-36.98,"pX":0,"scX":1,"skY":-36.98,"pY":0,"scY":1.06,"x":7.88}},{"z":1,"duration":3,"transform":{"y":14,"skX":-30,"pX":0,"scX":1,"skY":-30,"pY":-0.02,"scY":1.06,"x":7.88}},{"z":1,"duration":3,"transform":{"y":13.13,"skX":-36.98,"pX":0,"scX":1,"skY":-36.98,"pY":0,"scY":1.06,"x":7.88}},{"z":1,"duration":3,"transform":{"y":14,"skX":-30,"pX":0,"scX":1,"skY":-30,"pY":-0.02,"scY":1.06,"x":7.88}},{"z":1,"duration":1,"transform":{"y":13.13,"skX":-36.98,"pX":0,"scX":1,"skY":-36.98,"pY":0,"scY":1.06,"x":7.88}},{"displayIndex":-1,"duration":87}],"offset":0},{"name":"oslin","scale":1,"frame":[{"displayIndex":-1,"duration":9},{"z":14,"duration":1,"transform":{"y":33.35,"skX":-45,"pX":-0.05,"scX":0.36,"skY":-45,"pY":-0.05,"scY":0.36,"x":24.45}},{"z":14,"tweenEasing":0,"duration":5,"transform":{"y":13.65,"skX":34.61,"pX":-0.1,"scX":0.5,"skY":34.61,"pY":-0.12,"scY":0.43,"x":31.38}},{"z":14,"tweenEasing":0,"duration":2,"transform":{"y":11.1,"skX":54.8,"pX":-0.1,"scX":0.5,"skY":54.8,"pY":-0.07,"scY":0.43,"x":37.67}},{"z":14,"tweenEasing":0,"duration":2,"transform":{"y":35.28,"skX":-37.49,"pX":-0.12,"scX":0.59,"skY":-37.49,"pY":-0.07,"scY":0.47,"x":14.48}},{"z":14,"tweenEasing":0,"duration":3,"transform":{"y":50.98,"skX":0,"pX":0.03,"scX":0.66,"skY":0,"pY":-0.05,"scY":0.42,"x":28.13}},{"z":14,"tweenEasing":0,"duration":10,"transform":{"y":47.28,"skX":0,"pX":0,"scX":0.52,"skY":0,"pY":0,"scY":0.52,"x":31.55}},{"z":14,"duration":1,"transform":{"y":47.28,"skX":0,"pX":0,"scX":0.52,"skY":0,"pY":0,"scY":0.52,"x":31.55}},{"z":2,"tweenEasing":0,"duration":4,"transform":{"y":47.28,"skX":0,"pX":0,"scX":0.52,"skY":0,"pY":0,"scY":0.52,"x":31.55}},{"z":2,"tweenEasing":0,"duration":2,"transform":{"y":47.28,"skX":0,"pX":0,"scX":0.52,"skY":0,"pY":0,"scY":0.52,"x":31.55}},{"z":2,"tweenEasing":0,"duration":3,"transform":{"y":51.7,"skX":0,"pX":0.03,"scX":0.7,"skY":0,"pY":-0.02,"scY":0.38,"x":31.55}},{"z":2,"tweenEasing":0,"duration":3,"transform":{"y":47.28,"skX":0,"pX":0,"scX":0.52,"skY":0,"pY":0,"scY":0.52,"x":30.15}},{"z":2,"tweenEasing":0,"duration":3,"transform":{"y":47.28,"skX":0,"pX":0,"scX":0.52,"skY":0,"pY":0,"scY":0.52,"x":30.15}},{"z":2,"tweenEasing":0,"duration":3,"transform":{"y":47.28,"skX":0,"pX":0,"scX":0.52,"skY":0,"pY":0,"scY":0.52,"x":30.15}},{"z":2,"tweenEasing":0,"duration":3,"transform":{"y":47.28,"skX":0,"pX":0,"scX":0.52,"skY":0,"pY":0,"scY":0.52,"x":30.15}},{"z":2,"tweenEasing":0,"duration":3,"transform":{"y":47.28,"skX":0,"pX":0,"scX":0.52,"skY":0,"pY":0,"scY":0.52,"x":30.15}},{"z":2,"tweenEasing":0,"duration":3,"transform":{"y":47.28,"skX":0,"pX":0,"scX":0.52,"skY":0,"pY":0,"scY":0.52,"x":30.15}},{"z":2,"tweenEasing":0,"duration":3,"transform":{"y":47.28,"skX":0,"pX":0,"scX":0.52,"skY":0,"pY":0,"scY":0.52,"x":30.15}},{"z":2,"tweenEasing":0,"duration":3,"transform":{"y":47.28,"skX":0,"pX":0,"scX":0.52,"skY":0,"pY":0,"scY":0.52,"x":30.15}},{"z":2,"tweenEasing":0,"duration":3,"transform":{"y":47.28,"skX":0,"pX":0,"scX":0.52,"skY":0,"pY":0,"scY":0.52,"x":30.15}},{"z":2,"tweenEasing":0,"duration":3,"transform":{"y":47.28,"skX":0,"pX":0,"scX":0.52,"skY":0,"pY":0,"scY":0.52,"x":30.15}},{"z":2,"duration":1,"transform":{"y":47.28,"skX":0,"pX":0,"scX":0.52,"skY":0,"pY":0,"scY":0.52,"x":30.15}},{"z":2,"tweenEasing":0,"duration":6,"transform":{"y":47.28,"skX":0,"pX":0,"scX":0.52,"skY":0,"pY":0,"scY":0.52,"x":30.15}},{"z":2,"tweenEasing":0,"duration":6,"transform":{"y":47.28,"skX":0,"pX":0,"scX":0.52,"skY":0,"pY":0,"scY":0.52,"x":30.15}},{"z":2,"tweenEasing":0,"duration":7,"transform":{"y":47.28,"skX":0,"pX":0,"scX":0.52,"skY":0,"pY":0,"scY":0.52,"x":30.15}},{"z":2,"tweenEasing":0,"duration":6,"transform":{"y":47.28,"skX":0,"pX":0,"scX":0.52,"skY":0,"pY":0,"scY":0.52,"x":30.15}},{"z":2,"tweenEasing":0,"duration":6,"transform":{"y":47.28,"skX":0,"pX":0,"scX":0.52,"skY":0,"pY":0,"scY":0.52,"x":30.15}},{"z":2,"tweenEasing":0,"duration":6,"transform":{"y":47.28,"skX":0,"pX":0,"scX":0.52,"skY":0,"pY":0,"scY":0.52,"x":30.15}},{"z":2,"tweenEasing":0,"duration":7,"transform":{"y":47.28,"skX":0,"pX":0,"scX":0.52,"skY":0,"pY":0,"scY":0.52,"x":30.15}},{"z":2,"tweenEasing":0,"duration":6,"transform":{"y":47.28,"skX":0,"pX":0,"scX":0.52,"skY":0,"pY":0,"scY":0.52,"x":30.15}},{"z":2,"tweenEasing":0,"duration":7,"transform":{"y":47.28,"skX":0,"pX":0,"scX":0.52,"skY":0,"pY":0,"scY":0.52,"x":30.15}},{"z":2,"tweenEasing":0,"duration":3,"transform":{"y":47.28,"skX":0,"pX":0,"scX":0.52,"skY":0,"pY":0,"scY":0.52,"x":30.15}},{"z":2,"tweenEasing":0,"duration":3,"transform":{"y":47.28,"skX":0,"pX":0,"scX":0.52,"skY":0,"pY":0,"scY":0.52,"x":30.15}},{"z":2,"tweenEasing":0,"duration":3,"transform":{"y":47.28,"skX":0,"pX":0,"scX":0.52,"skY":0,"pY":0,"scY":0.52,"x":30.15}},{"z":2,"tweenEasing":0,"duration":3,"transform":{"y":47.28,"skX":0,"pX":0,"scX":0.52,"skY":0,"pY":0,"scY":0.52,"x":30.15}},{"z":2,"duration":1,"transform":{"y":47.28,"skX":0,"pX":0,"scX":0.52,"skY":0,"pY":0,"scY":0.52,"x":30.15}},{"z":14,"tweenEasing":0,"duration":6,"transform":{"y":47.28,"skX":0,"pX":0,"scX":0.52,"skY":0,"pY":0,"scY":0.52,"x":30.15}},{"z":14,"duration":1,"transform":{"y":47.28,"skX":0,"pX":0,"scX":0.52,"skY":0,"pY":0,"scY":0.52,"x":30.15}},{"z":14,"tweenEasing":0,"duration":4,"transform":{"y":47.28,"skX":0,"pX":0,"scX":0.52,"skY":0,"pY":0,"scY":0.52,"x":30.15}},{"z":14,"duration":1,"transform":{"y":36.92,"skX":45,"pX":-0.05,"scX":0.41,"skY":45,"pY":0,"scY":0.41,"x":32.85}},{"displayIndex":-1,"duration":5}],"offset":0},{"name":"legRight","scale":1,"frame":[{"z":3,"tweenEasing":0,"duration":6,"transform":{"y":54.25,"skX":-8.03,"pX":0,"scX":1,"skY":-8.03,"pY":-0.05,"scY":1.16,"x":39.83}},{"z":3,"tweenEasing":0,"duration":4,"transform":{"y":54.28,"skX":-8.01,"pX":0.03,"scX":1,"skY":-8.01,"pY":-0.07,"scY":1.16,"x":39.83}},{"z":3,"tweenEasing":0,"duration":5,"transform":{"y":54.28,"skX":-8.01,"pX":0.03,"scX":1,"skY":-8.01,"pY":-0.07,"scY":1.16,"x":39.83}},{"z":3,"tweenEasing":0,"duration":4,"transform":{"y":54.28,"skX":-8.01,"pX":0.03,"scX":1,"skY":-8.01,"pY":-0.07,"scY":1.16,"x":39.83}},{"z":3,"tweenEasing":0,"duration":3,"transform":{"y":54.28,"skX":-8.01,"pX":0.03,"scX":1,"skY":-8.01,"pY":-0.07,"scY":1.16,"x":39.83}},{"z":3,"tweenEasing":0,"duration":3,"transform":{"y":49.65,"skX":-8.03,"pX":0,"scX":1,"skY":-8.03,"pY":-0.05,"scY":1.16,"x":39.83}},{"z":3,"tweenEasing":0,"duration":3,"transform":{"y":49.65,"skX":-8.03,"pX":0,"scX":1,"skY":-8.03,"pY":-0.05,"scY":1.16,"x":39.83}},{"z":3,"tweenEasing":0,"duration":2,"transform":{"y":49.65,"skX":-8.03,"pX":0,"scX":1,"skY":-8.03,"pY":-0.05,"scY":1.16,"x":39.83}},{"z":3,"tweenEasing":0,"duration":3,"transform":{"y":49.65,"skX":-8.03,"pX":0,"scX":1,"skY":-8.03,"pY":-0.05,"scY":1.16,"x":39.83}},{"z":3,"tweenEasing":0,"duration":3,"transform":{"y":21.35,"skX":-16.17,"pX":0,"scX":1,"skY":-16.17,"pY":-0.05,"scY":1.16,"x":37.1}},{"z":3,"tweenEasing":0,"duration":3,"transform":{"y":-2.3,"skX":28.83,"pX":0,"scX":1,"skY":28.83,"pY":-0.05,"scY":1.16,"x":21.5}},{"z":3,"tweenEasing":0,"duration":3,"transform":{"y":46.85,"skX":-1.17,"pX":0,"scX":1,"skY":-1.17,"pY":-0.07,"scY":1.16,"x":27.65}},{"z":3,"tweenEasing":0,"duration":3,"transform":{"y":42.95,"skX":-1.17,"pX":0,"scX":1,"skY":-1.17,"pY":-0.1,"scY":1.16,"x":27.65}},{"z":3,"tweenEasing":0,"duration":3,"transform":{"y":42.95,"skX":-1.17,"pX":0,"scX":1,"skY":-1.17,"pY":-0.1,"scY":1.16,"x":27.65}},{"z":3,"tweenEasing":0,"duration":3,"transform":{"y":42.95,"skX":-1.17,"pX":0,"scX":1,"skY":-1.17,"pY":-0.1,"scY":1.16,"x":27.65}},{"z":3,"tweenEasing":0,"duration":3,"transform":{"y":42.95,"skX":-1.17,"pX":0,"scX":1,"skY":-1.17,"pY":-0.1,"scY":1.16,"x":27.65}},{"z":3,"tweenEasing":0,"duration":3,"transform":{"y":42.95,"skX":-1.17,"pX":0,"scX":1,"skY":-1.17,"pY":-0.1,"scY":1.16,"x":27.65}},{"z":3,"tweenEasing":0,"duration":3,"transform":{"y":42.95,"skX":-1.17,"pX":0,"scX":1,"skY":-1.17,"pY":-0.1,"scY":1.16,"x":27.65}},{"z":3,"tweenEasing":0,"duration":3,"transform":{"y":42.95,"skX":-1.17,"pX":0,"scX":1,"skY":-1.17,"pY":-0.1,"scY":1.16,"x":27.65}},{"z":3,"tweenEasing":0,"duration":3,"transform":{"y":42.95,"skX":-1.17,"pX":0,"scX":1,"skY":-1.17,"pY":-0.1,"scY":1.16,"x":27.65}},{"z":3,"tweenEasing":0,"duration":3,"transform":{"y":42.95,"skX":-1.17,"pX":0,"scX":1,"skY":-1.17,"pY":-0.1,"scY":1.16,"x":27.65}},{"z":3,"tweenEasing":0,"duration":3,"transform":{"y":42.95,"skX":-1.17,"pX":0,"scX":1,"skY":-1.17,"pY":-0.1,"scY":1.16,"x":27.65}},{"z":3,"duration":1,"transform":{"y":42.98,"skX":-1.17,"pX":0,"scX":1,"skY":-1.17,"pY":-0.1,"scY":0.92,"x":25.65}},{"z":3,"tweenEasing":0,"duration":6,"transform":{"y":42.98,"skX":-1.17,"pX":0,"scX":1,"skY":-1.17,"pY":-0.1,"scY":0.92,"x":25.65}},{"z":3,"tweenEasing":0,"duration":6,"transform":{"y":43,"skX":5.64,"pX":0,"scX":1,"skY":-1.17,"pY":-0.1,"scY":1.06,"x":25.65}},{"z":3,"tweenEasing":0,"duration":7,"transform":{"y":43,"skX":5.64,"pX":0,"scX":1,"skY":-1.17,"pY":-0.1,"scY":1.06,"x":25.65}},{"z":3,"tweenEasing":0,"duration":6,"transform":{"y":43,"skX":5.64,"pX":0,"scX":1,"skY":-1.17,"pY":-0.1,"scY":1.06,"x":25.65}},{"z":3,"tweenEasing":0,"duration":6,"transform":{"y":43,"skX":5.64,"pX":0,"scX":1,"skY":-1.17,"pY":-0.1,"scY":1.06,"x":25.65}},{"z":3,"tweenEasing":0,"duration":6,"transform":{"y":43,"skX":5.64,"pX":0,"scX":1,"skY":-1.17,"pY":-0.1,"scY":1.06,"x":25.65}},{"z":3,"tweenEasing":0,"duration":7,"transform":{"y":43,"skX":5.64,"pX":0,"scX":1,"skY":-1.17,"pY":-0.1,"scY":1.06,"x":25.65}},{"z":3,"tweenEasing":0,"duration":6,"transform":{"y":43,"skX":5.64,"pX":0,"scX":1,"skY":-1.17,"pY":-0.1,"scY":1.06,"x":25.65}},{"z":3,"tweenEasing":0,"duration":7,"transform":{"y":43,"skX":5.64,"pX":0,"scX":1,"skY":-1.17,"pY":-0.1,"scY":1.06,"x":25.65}},{"z":3,"tweenEasing":0,"duration":3,"transform":{"y":42.98,"skX":-1.17,"pX":0,"scX":1,"skY":-1.17,"pY":-0.1,"scY":0.92,"x":25.65}},{"z":3,"tweenEasing":0,"duration":3,"transform":{"y":42.98,"skX":-1.17,"pX":0,"scX":1,"skY":-1.17,"pY":-0.1,"scY":0.92,"x":25.65}},{"z":3,"tweenEasing":0,"duration":3,"transform":{"y":42.98,"skX":-1.17,"pX":0,"scX":1,"skY":-1.17,"pY":-0.1,"scY":0.92,"x":25.65}},{"z":3,"tweenEasing":0,"duration":3,"transform":{"y":30.03,"skX":11.44,"pX":0.03,"scX":1,"skY":11.44,"pY":-0.07,"scY":1.01,"x":33.8}},{"z":3,"tweenEasing":0,"duration":2,"transform":{"y":6.25,"skX":26.44,"pX":0,"scX":1,"skY":26.44,"pY":-0.05,"scY":1.01,"x":43.4}},{"z":3,"tweenEasing":0,"duration":3,"transform":{"y":54.25,"skX":-8.03,"pX":0,"scX":1,"skY":-8.03,"pY":-0.05,"scY":1.16,"x":39.83}},{"z":3,"tweenEasing":0,"duration":3,"transform":{"y":54.25,"skX":-8.03,"pX":0,"scX":1,"skY":-8.03,"pY":-0.05,"scY":1.16,"x":39.83}},{"z":3,"tweenEasing":0,"duration":4,"transform":{"y":54.25,"skX":-8.03,"pX":0,"scX":1,"skY":-8.03,"pY":-0.05,"scY":1.16,"x":39.83}},{"z":3,"tweenEasing":0,"duration":5,"transform":{"y":54.25,"skX":-8.03,"pX":0,"scX":1,"skY":-8.03,"pY":-0.05,"scY":1.16,"x":39.83}},{"z":3,"duration":1,"transform":{"y":54.25,"skX":-8.03,"pX":0,"scX":1,"skY":-8.03,"pY":-0.05,"scY":1.16,"x":39.83}}],"offset":0},{"name":"tail","scale":1,"frame":[{"z":4,"tweenEasing":0,"duration":6,"transform":{"y":37.38,"skX":-59.95,"pX":0,"scX":1,"skY":-59.95,"pY":0,"scY":1,"x":44.98}},{"z":4,"tweenEasing":0,"duration":4,"transform":{"y":38.42,"skX":-49.97,"pX":-0.02,"scX":1,"skY":-49.97,"pY":0.03,"scY":1,"x":45.7}},{"z":4,"tweenEasing":0,"duration":5,"transform":{"y":40.6,"skX":-34.97,"pX":-0.05,"scX":1,"skY":-34.97,"pY":-0.02,"scY":1,"x":46.3}},{"z":4,"tweenEasing":0,"duration":4,"transform":{"y":41.2,"skX":-29.78,"pX":0,"scX":1,"skY":-29.78,"pY":0,"scY":1,"x":46.43}},{"z":4,"tweenEasing":0,"duration":3,"transform":{"y":39.53,"skX":-102.7,"pX":-0.05,"scX":1,"skY":-102.7,"pY":-0.02,"scY":1,"x":42.4}},{"z":4,"tweenEasing":0,"duration":3,"transform":{"y":32.78,"skX":-59.95,"pX":0,"scX":1,"skY":-59.95,"pY":0.03,"scY":1,"x":44.98}},{"z":4,"tweenEasing":0,"duration":3,"transform":{"y":32.78,"skX":-59.95,"pX":0,"scX":1,"skY":-59.95,"pY":0.03,"scY":1,"x":44.98}},{"z":4,"tweenEasing":0,"duration":2,"transform":{"y":34.92,"skX":-59.95,"pX":0,"scX":1,"skY":-59.95,"pY":0,"scY":1,"x":44.98}},{"z":4,"tweenEasing":0,"duration":3,"transform":{"y":39.08,"skX":-71.67,"pX":0,"scX":1,"skY":-71.67,"pY":0,"scY":1,"x":48.9}},{"z":4,"tweenEasing":0,"duration":3,"transform":{"y":6.05,"skX":-68.09,"pX":-0.02,"scX":1,"skY":-68.09,"pY":0.03,"scY":1,"x":40.13}},{"z":4,"tweenEasing":0,"duration":3,"transform":{"y":-9.22,"skX":-8.09,"pX":0.03,"scX":1,"skY":-8.09,"pY":0.03,"scY":1,"x":31.55}},{"z":4,"tweenEasing":0,"duration":3,"transform":{"y":32.85,"skX":-53.09,"pX":-0.02,"scX":1,"skY":-53.09,"pY":0.03,"scY":1,"x":34.53}},{"z":4,"tweenEasing":0,"duration":3,"transform":{"y":28.95,"skX":-53.09,"pX":-0.02,"scX":1,"skY":-53.09,"pY":0.03,"scY":1,"x":34.53}},{"z":4,"tweenEasing":0,"duration":3,"transform":{"y":25.1,"skX":-76.29,"pX":-0.02,"scX":1,"skY":-76.29,"pY":0.08,"scY":1,"x":32.92}},{"z":4,"tweenEasing":0,"duration":3,"transform":{"y":25.1,"skX":-76.29,"pX":-0.02,"scX":1,"skY":-76.29,"pY":0.08,"scY":1,"x":32.92}},{"z":4,"tweenEasing":0,"duration":3,"transform":{"y":25.1,"skX":-76.29,"pX":-0.02,"scX":1,"skY":-76.29,"pY":0.08,"scY":1,"x":32.92}},{"z":4,"tweenEasing":0,"duration":3,"transform":{"y":25.1,"skX":-76.29,"pX":-0.02,"scX":1,"skY":-76.29,"pY":0.08,"scY":1,"x":32.92}},{"z":4,"tweenEasing":0,"duration":3,"transform":{"y":25.1,"skX":-76.29,"pX":-0.02,"scX":1,"skY":-76.29,"pY":0.08,"scY":1,"x":32.92}},{"z":4,"tweenEasing":0,"duration":3,"transform":{"y":25.1,"skX":-76.29,"pX":-0.02,"scX":1,"skY":-76.29,"pY":0.08,"scY":1,"x":32.92}},{"z":4,"tweenEasing":0,"duration":3,"transform":{"y":25.1,"skX":-76.29,"pX":-0.02,"scX":1,"skY":-76.29,"pY":0.08,"scY":1,"x":32.92}},{"z":4,"tweenEasing":0,"duration":3,"transform":{"y":25.1,"skX":-76.29,"pX":-0.02,"scX":1,"skY":-76.29,"pY":0.08,"scY":1,"x":32.92}},{"z":4,"tweenEasing":0,"duration":3,"transform":{"y":25.18,"skX":-84.23,"pX":-0.02,"scX":1,"skY":-84.23,"pY":0.08,"scY":1,"x":32.38}},{"z":4,"duration":1,"transform":{"y":28.38,"skX":-54.23,"pX":-0.05,"scX":1,"skY":-54.23,"pY":0.03,"scY":1,"x":34.65}},{"z":4,"tweenEasing":0,"duration":6,"transform":{"y":28.38,"skX":-54.23,"pX":-0.05,"scX":1,"skY":-54.23,"pY":0.03,"scY":1,"x":34.65}},{"z":4,"tweenEasing":0,"duration":6,"transform":{"y":30.23,"skX":-35.76,"pX":0,"scX":1,"skY":-35.76,"pY":0.03,"scY":1,"x":35.48}},{"z":4,"tweenEasing":0,"duration":7,"transform":{"y":30.23,"skX":-35.76,"pX":0,"scX":1,"skY":-35.76,"pY":0.03,"scY":1,"x":35.48}},{"z":4,"tweenEasing":0,"duration":6,"transform":{"y":30.23,"skX":-35.76,"pX":0,"scX":1,"skY":-35.76,"pY":0.03,"scY":1,"x":35.48}},{"z":4,"tweenEasing":0,"duration":6,"transform":{"y":30.23,"skX":-35.76,"pX":0,"scX":1,"skY":-35.76,"pY":0.03,"scY":1,"x":35.48}},{"z":4,"tweenEasing":0,"duration":6,"transform":{"y":30.23,"skX":-35.76,"pX":0,"scX":1,"skY":-35.76,"pY":0.03,"scY":1,"x":35.48}},{"z":4,"tweenEasing":0,"duration":7,"transform":{"y":30.23,"skX":-35.76,"pX":0,"scX":1,"skY":-35.76,"pY":0.03,"scY":1,"x":35.48}},{"z":4,"tweenEasing":0,"duration":6,"transform":{"y":30.23,"skX":-35.76,"pX":0,"scX":1,"skY":-35.76,"pY":0.03,"scY":1,"x":35.48}},{"z":4,"tweenEasing":0,"duration":7,"transform":{"y":30.23,"skX":-35.76,"pX":0,"scX":1,"skY":-35.76,"pY":0.03,"scY":1,"x":35.48}},{"z":4,"tweenEasing":0,"duration":3,"transform":{"y":28.38,"skX":-54.23,"pX":-0.05,"scX":1,"skY":-54.23,"pY":0.03,"scY":1,"x":34.65}},{"z":4,"tweenEasing":0,"duration":3,"transform":{"y":28.38,"skX":-54.23,"pX":-0.05,"scX":1,"skY":-54.23,"pY":0.03,"scY":1,"x":34.65}},{"z":4,"tweenEasing":0,"duration":3,"transform":{"y":32.2,"skX":-69.23,"pX":-0.05,"scX":1,"skY":-69.23,"pY":0.03,"scY":1,"x":34.65}},{"z":4,"tweenEasing":0,"duration":3,"transform":{"y":16.6,"skX":-50.72,"pX":-0.07,"scX":1,"skY":-50.72,"pY":0.03,"scY":1,"x":45.2}},{"z":4,"tweenEasing":0,"duration":2,"transform":{"y":1.38,"skX":-65.72,"pX":-0.05,"scX":1,"skY":-65.72,"pY":0.08,"scY":1,"x":56.08}},{"z":4,"tweenEasing":0,"duration":3,"transform":{"y":43.28,"skX":-74.95,"pX":-0.02,"scX":1,"skY":-74.95,"pY":0.03,"scY":1,"x":46.1}},{"z":4,"tweenEasing":0,"duration":3,"transform":{"y":37.38,"skX":-59.95,"pX":0,"scX":1,"skY":-59.95,"pY":0,"scY":1,"x":44.98}},{"z":4,"tweenEasing":0,"duration":4,"transform":{"y":38.05,"skX":-74.95,"pX":0,"scX":1,"skY":-74.95,"pY":-0.05,"scY":1,"x":44.08}},{"z":4,"tweenEasing":0,"duration":5,"transform":{"y":37.38,"skX":-59.95,"pX":0,"scX":1,"skY":-59.95,"pY":0,"scY":1,"x":44.98}},{"z":4,"duration":1,"transform":{"y":37.38,"skX":-59.95,"pX":0,"scX":1,"skY":-59.95,"pY":0,"scY":1,"x":44.98}}],"offset":0},{"name":"handRight","scale":1,"frame":[{"z":5,"tweenEasing":0,"duration":6,"transform":{"y":24.5,"skX":-4.23,"pX":-0.05,"scX":1,"skY":-4.23,"pY":-0.02,"scY":1.17,"x":36.65}},{"z":5,"tweenEasing":0,"duration":4,"transform":{"y":24.35,"skX":-1.6,"pX":-0.1,"scX":1,"skY":-1.6,"pY":-0.12,"scY":0.74,"x":39.75}},{"z":5,"tweenEasing":0,"duration":5,"transform":{"y":25.45,"skX":88.39,"pX":-0.05,"scX":1,"skY":88.39,"pY":-0.1,"scY":1.06,"x":44.18}},{"z":5,"tweenEasing":0,"duration":4,"transform":{"y":26.6,"skX":108.58,"pX":-0.02,"scX":1,"skY":108.59,"pY":-0.02,"scY":1.06,"x":45.63}},{"z":5,"tweenEasing":0,"duration":3,"transform":{"y":35.78,"skX":20.66,"pX":0,"scX":1,"skY":20.66,"pY":-0.12,"scY":1.06,"x":27.55}},{"z":5,"tweenEasing":0,"duration":3,"transform":{"y":19.9,"skX":-4.23,"pX":-0.02,"scX":1,"skY":-4.23,"pY":-0.02,"scY":1.17,"x":36.65}},{"z":5,"tweenEasing":0,"duration":3,"transform":{"y":19.9,"skX":-4.23,"pX":-0.02,"scX":1,"skY":-4.23,"pY":-0.02,"scY":1.17,"x":36.65}},{"z":5,"tweenEasing":0,"duration":2,"transform":{"y":22.05,"skX":-4.23,"pX":-0.05,"scX":1,"skY":-4.23,"pY":-0.05,"scY":1.17,"x":36.65}},{"z":5,"tweenEasing":0,"duration":3,"transform":{"y":28.15,"skX":-15.94,"pX":-0.05,"scX":1,"skY":-15.94,"pY":-0.02,"scY":1.17,"x":38.1}},{"z":5,"tweenEasing":0,"duration":3,"transform":{"y":-5.5,"skX":-12.37,"pX":-0.05,"scX":1,"skY":-12.37,"pY":-0.05,"scY":1.17,"x":30.08}},{"z":5,"tweenEasing":0,"duration":3,"transform":{"y":-20.8,"skX":-12.37,"pX":-0.02,"scX":1,"skY":-12.37,"pY":-0.05,"scY":1.17,"x":21.5}},{"z":5,"tweenEasing":0,"duration":3,"transform":{"y":19.1,"skX":2.63,"pX":-0.05,"scX":1,"skY":2.63,"pY":-0.02,"scY":1.17,"x":27.8}},{"z":5,"tweenEasing":0,"duration":3,"transform":{"y":15.2,"skX":2.63,"pX":-0.05,"scX":1,"skY":2.63,"pY":-0.02,"scY":1.17,"x":27.8}},{"z":5,"tweenEasing":0,"duration":3,"transform":{"y":15.08,"skX":54.43,"pX":-0.02,"scX":1,"skY":54.43,"pY":0,"scY":0.8,"x":21.33}},{"z":5,"tweenEasing":0,"duration":3,"transform":{"y":15.08,"skX":9.44,"pX":-0.02,"scX":1,"skY":9.43,"pY":0.03,"scY":0.8,"x":21.33}},{"z":5,"tweenEasing":0,"duration":3,"transform":{"y":15.08,"skX":54.43,"pX":-0.02,"scX":1,"skY":54.43,"pY":0,"scY":0.8,"x":21.33}},{"z":5,"tweenEasing":0,"duration":3,"transform":{"y":15.08,"skX":9.44,"pX":-0.02,"scX":1,"skY":9.43,"pY":0.03,"scY":0.8,"x":21.33}},{"z":5,"tweenEasing":0,"duration":3,"transform":{"y":15.08,"skX":54.43,"pX":-0.02,"scX":1,"skY":54.43,"pY":0,"scY":0.8,"x":21.33}},{"z":5,"tweenEasing":0,"duration":3,"transform":{"y":15.08,"skX":9.44,"pX":-0.02,"scX":1,"skY":9.43,"pY":0.03,"scY":0.8,"x":21.33}},{"z":5,"tweenEasing":0,"duration":3,"transform":{"y":15.08,"skX":54.43,"pX":-0.02,"scX":1,"skY":54.43,"pY":0,"scY":0.8,"x":21.33}},{"z":5,"tweenEasing":0,"duration":3,"transform":{"y":15.08,"skX":9.44,"pX":-0.02,"scX":1,"skY":9.43,"pY":0.03,"scY":0.8,"x":21.33}},{"z":5,"tweenEasing":0,"duration":3,"transform":{"y":16.85,"skX":46.5,"pX":-0.02,"scX":1,"skY":46.5,"pY":0.05,"scY":0.8,"x":19.52}},{"z":5,"duration":1,"transform":{"y":14.75,"skX":76.5,"pX":-0.02,"scX":1,"skY":76.49,"pY":0,"scY":0.8,"x":27.63}},{"z":5,"tweenEasing":0,"duration":6,"transform":{"y":14.75,"skX":76.5,"pX":-0.02,"scX":1,"skY":76.49,"pY":0,"scY":0.8,"x":27.63}},{"z":5,"tweenEasing":0,"duration":6,"transform":{"y":15.08,"skX":94.96,"pX":-0.02,"scX":1,"skY":94.96,"pY":0.03,"scY":0.8,"x":33.15}},{"z":5,"tweenEasing":0,"duration":7,"transform":{"y":15.08,"skX":94.96,"pX":-0.02,"scX":1,"skY":94.96,"pY":0.03,"scY":0.8,"x":33.15}},{"z":5,"tweenEasing":0,"duration":6,"transform":{"y":15.08,"skX":94.96,"pX":-0.02,"scX":1,"skY":94.96,"pY":0.03,"scY":0.8,"x":33.15}},{"z":5,"tweenEasing":0,"duration":6,"transform":{"y":15.08,"skX":94.96,"pX":-0.02,"scX":1,"skY":94.96,"pY":0.03,"scY":0.8,"x":33.15}},{"z":5,"tweenEasing":0,"duration":6,"transform":{"y":15.08,"skX":94.96,"pX":-0.02,"scX":1,"skY":94.96,"pY":0.03,"scY":0.8,"x":33.15}},{"z":5,"tweenEasing":0,"duration":7,"transform":{"y":15.08,"skX":94.96,"pX":-0.02,"scX":1,"skY":94.96,"pY":0.03,"scY":0.8,"x":33.15}},{"z":5,"tweenEasing":0,"duration":6,"transform":{"y":15.08,"skX":94.96,"pX":-0.02,"scX":1,"skY":94.96,"pY":0.03,"scY":0.8,"x":33.15}},{"z":5,"tweenEasing":0,"duration":7,"transform":{"y":15.08,"skX":94.96,"pX":-0.02,"scX":1,"skY":94.96,"pY":0.03,"scY":0.8,"x":33.15}},{"z":5,"tweenEasing":0,"duration":3,"transform":{"y":14.75,"skX":76.5,"pX":-0.02,"scX":1,"skY":76.49,"pY":0,"scY":0.8,"x":27.63}},{"z":5,"tweenEasing":0,"duration":3,"transform":{"y":14.73,"skX":1.5,"pX":-0.02,"scX":1,"skY":1.49,"pY":0.03,"scY":0.8,"x":27.63}},{"z":5,"tweenEasing":0,"duration":3,"transform":{"y":20.85,"skX":-13.5,"pX":-0.05,"scX":1,"skY":-13.51,"pY":0,"scY":0.8,"x":24.33}},{"z":5,"tweenEasing":0,"duration":3,"transform":{"y":2.6,"skX":4.99,"pX":-0.02,"scX":1,"skY":4.99,"pY":0,"scY":0.93,"x":39}},{"z":5,"tweenEasing":0,"duration":2,"transform":{"y":-10.55,"skX":-10.01,"pX":-0.05,"scX":1,"skY":-10.01,"pY":0.03,"scY":0.93,"x":46.5}},{"z":5,"tweenEasing":0,"duration":3,"transform":{"y":33,"skX":-19.23,"pX":-0.02,"scX":1,"skY":-19.23,"pY":-0.05,"scY":1.17,"x":34.75}},{"z":5,"tweenEasing":0,"duration":3,"transform":{"y":24.5,"skX":-4.23,"pX":-0.05,"scX":1,"skY":-4.23,"pY":-0.02,"scY":1.17,"x":36.65}},{"z":5,"tweenEasing":0,"duration":4,"transform":{"y":27.8,"skX":-19.23,"pX":-0.07,"scX":1,"skY":-19.23,"pY":-0.05,"scY":1.17,"x":32.7}},{"z":5,"tweenEasing":0,"duration":5,"transform":{"y":24.5,"skX":-4.23,"pX":-0.05,"scX":1,"skY":-4.23,"pY":-0.02,"scY":1.17,"x":36.65}},{"z":5,"duration":1,"transform":{"y":24.5,"skX":-4.23,"pX":-0.05,"scX":1,"skY":-4.23,"pY":-0.02,"scY":1.17,"x":36.65}}],"offset":0},{"name":"body","scale":1,"frame":[{"z":6,"tweenEasing":0,"duration":6,"transform":{"y":42.78,"skX":-4.05,"pX":0,"scX":1,"skY":-4.05,"pY":0,"scY":0.93,"x":42.23}},{"z":6,"tweenEasing":0,"duration":4,"transform":{"y":43.28,"skX":5.96,"pX":0,"scX":1,"skY":5.96,"pY":0,"scY":0.93,"x":42.05}},{"z":6,"tweenEasing":0,"duration":5,"transform":{"y":44.33,"skX":20.96,"pX":0,"scX":1,"skY":20.96,"pY":0,"scY":0.93,"x":41.5}},{"z":6,"tweenEasing":0,"duration":4,"transform":{"y":44.48,"skX":26.15,"pX":0,"scX":1,"skY":26.15,"pY":0,"scY":0.93,"x":41.33}},{"z":6,"tweenEasing":0,"duration":3,"transform":{"y":45.38,"skX":-46.78,"pX":0,"scX":1,"skY":-46.77,"pY":0,"scY":0.93,"x":44.05}},{"z":6,"tweenEasing":0,"duration":3,"transform":{"y":38.17,"skX":-4.05,"pX":0,"scX":1,"skY":-4.05,"pY":0,"scY":0.93,"x":42.23}},{"z":6,"tweenEasing":0,"duration":3,"transform":{"y":38.17,"skX":-4.05,"pX":0,"scX":1,"skY":-4.05,"pY":0,"scY":0.93,"x":42.23}},{"z":6,"tweenEasing":0,"duration":2,"transform":{"y":40.33,"skX":-4.05,"pX":0,"scX":1,"skY":-4.05,"pY":0,"scY":0.93,"x":42.23}},{"z":6,"tweenEasing":0,"duration":3,"transform":{"y":44.9,"skX":-15.76,"pX":0,"scX":1,"skY":-15.76,"pY":0,"scY":0.93,"x":47.28}},{"z":6,"tweenEasing":0,"duration":3,"transform":{"y":11.8,"skX":-12.19,"pX":0,"scX":1,"skY":-12.19,"pY":0,"scY":0.93,"x":38.17}},{"z":6,"tweenEasing":0,"duration":3,"transform":{"y":-3.5,"skX":-12.19,"pX":0,"scX":1,"skY":-12.19,"pY":0,"scY":0.93,"x":29.6}},{"z":6,"tweenEasing":0,"duration":3,"transform":{"y":37.9,"skX":2.81,"pX":0,"scX":1,"skY":2.81,"pY":0,"scY":0.93,"x":31.15}},{"z":6,"tweenEasing":0,"duration":3,"transform":{"y":34,"skX":2.81,"pX":0,"scX":1,"skY":2.81,"pY":0,"scY":0.93,"x":31.15}},{"z":6,"tweenEasing":0,"duration":3,"transform":{"y":31.08,"skX":-20.39,"pX":0,"scX":1,"skY":-20.39,"pY":0,"scY":0.93,"x":31.83}},{"z":6,"tweenEasing":0,"duration":3,"transform":{"y":31.08,"skX":-20.39,"pX":0,"scX":1,"skY":-20.39,"pY":0,"scY":0.93,"x":31.83}},{"z":6,"tweenEasing":0,"duration":3,"transform":{"y":31.08,"skX":-20.39,"pX":0,"scX":1,"skY":-20.39,"pY":0,"scY":0.93,"x":31.83}},{"z":6,"tweenEasing":0,"duration":3,"transform":{"y":31.08,"skX":-20.39,"pX":0,"scX":1,"skY":-20.39,"pY":0,"scY":0.93,"x":31.83}},{"z":6,"tweenEasing":0,"duration":3,"transform":{"y":31.08,"skX":-20.39,"pX":0,"scX":1,"skY":-20.39,"pY":0,"scY":0.93,"x":31.83}},{"z":6,"tweenEasing":0,"duration":3,"transform":{"y":31.08,"skX":-20.39,"pX":0,"scX":1,"skY":-20.39,"pY":0,"scY":0.93,"x":31.83}},{"z":6,"tweenEasing":0,"duration":3,"transform":{"y":31.08,"skX":-20.39,"pX":0,"scX":1,"skY":-20.39,"pY":0,"scY":0.93,"x":31.83}},{"z":6,"tweenEasing":0,"duration":3,"transform":{"y":31.08,"skX":-20.39,"pX":0,"scX":1,"skY":-20.39,"pY":0,"scY":0.93,"x":31.83}},{"z":6,"tweenEasing":0,"duration":3,"transform":{"y":31.25,"skX":-28.32,"pX":0,"scX":1,"skY":-28.32,"pY":0,"scY":0.93,"x":32.13}},{"z":6,"duration":1,"transform":{"y":33.53,"skX":1.68,"pX":0,"scX":1,"skY":1.67,"pY":0,"scY":0.93,"x":31.35}},{"z":6,"tweenEasing":0,"duration":6,"transform":{"y":33.53,"skX":1.68,"pX":0,"scX":1,"skY":1.67,"pY":0,"scY":0.93,"x":31.35}},{"z":6,"tweenEasing":0,"duration":6,"transform":{"y":34.05,"skX":20.14,"pX":0,"scX":1,"skY":20.14,"pY":0,"scY":0.93,"x":30.73}},{"z":6,"tweenEasing":0,"duration":7,"transform":{"y":34.05,"skX":20.04,"pX":0,"scX":1.04,"skY":20.04,"pY":0,"scY":0.93,"x":30.4}},{"z":6,"tweenEasing":0,"duration":6,"transform":{"y":34.05,"skX":20.14,"pX":0,"scX":1,"skY":20.14,"pY":0,"scY":0.93,"x":30.73}},{"z":6,"tweenEasing":0,"duration":6,"transform":{"y":34.05,"skX":20.04,"pX":0,"scX":1.04,"skY":20.04,"pY":0,"scY":0.93,"x":30.4}},{"z":6,"tweenEasing":0,"duration":6,"transform":{"y":34.05,"skX":20.14,"pX":0,"scX":1,"skY":20.14,"pY":0,"scY":0.93,"x":30.73}},{"z":6,"tweenEasing":0,"duration":7,"transform":{"y":34.05,"skX":20.04,"pX":0,"scX":1.04,"skY":20.04,"pY":0,"scY":0.93,"x":30.4}},{"z":6,"tweenEasing":0,"duration":6,"transform":{"y":34.05,"skX":20.14,"pX":0,"scX":1,"skY":20.14,"pY":0,"scY":0.93,"x":30.73}},{"z":6,"tweenEasing":0,"duration":7,"transform":{"y":34.05,"skX":20.04,"pX":0,"scX":1.04,"skY":20.04,"pY":0,"scY":0.93,"x":30.4}},{"z":6,"tweenEasing":0,"duration":3,"transform":{"y":33.53,"skX":1.68,"pX":0,"scX":1,"skY":1.67,"pY":0,"scY":0.93,"x":31.35}},{"z":6,"tweenEasing":0,"duration":3,"transform":{"y":33.53,"skX":1.68,"pX":0,"scX":1,"skY":1.67,"pY":0,"scY":0.93,"x":31.35}},{"z":6,"tweenEasing":0,"duration":3,"transform":{"y":38.03,"skX":-13.32,"pX":0,"scX":1,"skY":-13.32,"pY":0,"scY":0.93,"x":32.8}},{"z":6,"tweenEasing":0,"duration":3,"transform":{"y":21.48,"skX":5.22,"pX":0,"scX":1,"skY":5.22,"pY":0,"scY":0.93,"x":41.58}},{"z":6,"tweenEasing":0,"duration":2,"transform":{"y":7.05,"skX":-9.78,"pX":0,"scX":1,"skY":-9.78,"pY":0,"scY":0.93,"x":53.85}},{"z":6,"tweenEasing":0,"duration":3,"transform":{"y":49.2,"skX":-19.05,"pX":0,"scX":1,"skY":-19.05,"pY":0,"scY":0.93,"x":44.85}},{"z":6,"tweenEasing":0,"duration":3,"transform":{"y":42.78,"skX":-4.05,"pX":0,"scX":1,"skY":-4.05,"pY":0,"scY":0.93,"x":42.23}},{"z":6,"tweenEasing":0,"duration":4,"transform":{"y":44,"skX":-19.05,"pX":0,"scX":1,"skY":-19.05,"pY":0,"scY":0.93,"x":42.8}},{"z":6,"tweenEasing":0,"duration":5,"transform":{"y":42.78,"skX":-4.05,"pX":0,"scX":1,"skY":-4.05,"pY":0,"scY":0.93,"x":42.23}},{"z":6,"duration":1,"transform":{"y":42.78,"skX":-4.05,"pX":0,"scX":1,"skY":-4.05,"pY":0,"scY":0.93,"x":42.23}}],"offset":0},{"name":"legLeft","scale":1,"frame":[{"z":7,"tweenEasing":0,"duration":6,"transform":{"y":56.33,"skX":0,"pX":0,"scX":1,"skY":0,"pY":0,"scY":1.21,"x":46}},{"z":7,"tweenEasing":0,"duration":4,"transform":{"y":56.33,"skX":0,"pX":0,"scX":1,"skY":0,"pY":0,"scY":1.21,"x":46}},{"z":7,"tweenEasing":0,"duration":5,"transform":{"y":56.33,"skX":0,"pX":0,"scX":1,"skY":0,"pY":0,"scY":1.05,"x":46}},{"z":7,"tweenEasing":0,"duration":4,"transform":{"y":56.33,"skX":0,"pX":0,"scX":1,"skY":0,"pY":0,"scY":1.01,"x":46}},{"z":7,"tweenEasing":0,"duration":3,"transform":{"y":40.17,"skX":-90,"pX":0,"scX":1,"skY":-90,"pY":0,"scY":1.21,"x":60.2}},{"z":7,"tweenEasing":0,"duration":3,"transform":{"y":51.73,"skX":0,"pX":0,"scX":1,"skY":0,"pY":0,"scY":1.21,"x":46}},{"z":7,"tweenEasing":0,"duration":3,"transform":{"y":51.73,"skX":0,"pX":0,"scX":1,"skY":0,"pY":0,"scY":1.21,"x":46}},{"z":7,"tweenEasing":0,"duration":2,"transform":{"y":51.73,"skX":0,"pX":0,"scX":1,"skY":0,"pY":0,"scY":1,"x":46}},{"z":7,"tweenEasing":0,"duration":3,"transform":{"y":51.73,"skX":30,"pX":-0.02,"scX":1,"skY":30,"pY":0,"scY":1,"x":46}},{"z":7,"tweenEasing":0,"duration":3,"transform":{"y":22.55,"skX":-8.14,"pX":0.03,"scX":1,"skY":-8.14,"pY":-0.02,"scY":1,"x":43.5}},{"z":7,"tweenEasing":0,"duration":3,"transform":{"y":3.1,"skX":36.86,"pX":0,"scX":1,"skY":36.86,"pY":0.03,"scY":1,"x":25.23}},{"z":7,"tweenEasing":0,"duration":3,"transform":{"y":49.68,"skX":6.86,"pX":0.03,"scX":1,"skY":6.86,"pY":0,"scY":1,"x":33.55}},{"z":7,"tweenEasing":0,"duration":3,"transform":{"y":45.78,"skX":6.86,"pX":0,"scX":1,"skY":6.86,"pY":0,"scY":1,"x":33.55}},{"z":7,"tweenEasing":0,"duration":3,"transform":{"y":45.85,"skX":6.86,"pX":0,"scX":1,"skY":6.86,"pY":-0.07,"scY":1.31,"x":33.55}},{"z":7,"tweenEasing":0,"duration":3,"transform":{"y":45.85,"skX":6.86,"pX":0,"scX":1,"skY":6.86,"pY":-0.07,"scY":1.31,"x":33.55}},{"z":7,"tweenEasing":0,"duration":3,"transform":{"y":45.85,"skX":6.86,"pX":0,"scX":1,"skY":6.86,"pY":-0.07,"scY":1.31,"x":33.55}},{"z":7,"tweenEasing":0,"duration":3,"transform":{"y":45.85,"skX":6.86,"pX":0,"scX":1,"skY":6.86,"pY":-0.07,"scY":1.31,"x":33.55}},{"z":7,"tweenEasing":0,"duration":3,"transform":{"y":45.85,"skX":6.86,"pX":0,"scX":1,"skY":6.86,"pY":-0.07,"scY":1.31,"x":33.55}},{"z":7,"tweenEasing":0,"duration":3,"transform":{"y":45.85,"skX":6.86,"pX":0,"scX":1,"skY":6.86,"pY":-0.07,"scY":1.31,"x":33.55}},{"z":7,"tweenEasing":0,"duration":3,"transform":{"y":45.85,"skX":6.86,"pX":0,"scX":1,"skY":6.86,"pY":-0.07,"scY":1.31,"x":33.55}},{"z":7,"tweenEasing":0,"duration":3,"transform":{"y":45.85,"skX":6.86,"pX":0,"scX":1,"skY":6.86,"pY":-0.07,"scY":1.31,"x":33.55}},{"z":7,"tweenEasing":0,"duration":3,"transform":{"y":45.85,"skX":6.86,"pX":0,"scX":1,"skY":6.86,"pY":-0.07,"scY":1.31,"x":33.55}},{"z":7,"duration":1,"transform":{"y":45.88,"skX":6.86,"pX":0.03,"scX":1,"skY":6.86,"pY":-0.1,"scY":1.16,"x":33.53}},{"z":7,"tweenEasing":0,"duration":6,"transform":{"y":45.88,"skX":6.86,"pX":0.03,"scX":1,"skY":6.86,"pY":-0.1,"scY":1.16,"x":33.53}},{"z":7,"tweenEasing":0,"duration":6,"transform":{"y":45.88,"skX":6.86,"pX":0.03,"scX":1,"skY":6.86,"pY":-0.05,"scY":0.89,"x":33.53}},{"z":7,"tweenEasing":0,"duration":7,"transform":{"y":45.88,"skX":6.86,"pX":0.03,"scX":1,"skY":6.86,"pY":-0.05,"scY":0.89,"x":33.53}},{"z":7,"tweenEasing":0,"duration":6,"transform":{"y":45.88,"skX":6.86,"pX":0.03,"scX":1,"skY":6.86,"pY":-0.05,"scY":0.89,"x":33.53}},{"z":7,"tweenEasing":0,"duration":6,"transform":{"y":45.88,"skX":6.86,"pX":0.03,"scX":1,"skY":6.86,"pY":-0.05,"scY":0.89,"x":33.53}},{"z":7,"tweenEasing":0,"duration":6,"transform":{"y":45.88,"skX":6.86,"pX":0.03,"scX":1,"skY":6.86,"pY":-0.05,"scY":0.89,"x":33.53}},{"z":7,"tweenEasing":0,"duration":7,"transform":{"y":45.88,"skX":6.86,"pX":0.03,"scX":1,"skY":6.86,"pY":-0.05,"scY":0.89,"x":33.53}},{"z":7,"tweenEasing":0,"duration":6,"transform":{"y":45.88,"skX":6.86,"pX":0.03,"scX":1,"skY":6.86,"pY":-0.05,"scY":0.89,"x":33.53}},{"z":7,"tweenEasing":0,"duration":7,"transform":{"y":45.88,"skX":6.86,"pX":0.03,"scX":1,"skY":6.86,"pY":-0.05,"scY":0.89,"x":33.53}},{"z":7,"tweenEasing":0,"duration":3,"transform":{"y":45.88,"skX":6.86,"pX":0.03,"scX":1,"skY":6.86,"pY":-0.1,"scY":1.16,"x":33.53}},{"z":7,"tweenEasing":0,"duration":3,"transform":{"y":45.88,"skX":6.86,"pX":0.03,"scX":1,"skY":6.86,"pY":-0.1,"scY":1.16,"x":33.53}},{"z":7,"tweenEasing":0,"duration":3,"transform":{"y":45.88,"skX":6.86,"pX":0.05,"scX":1,"skY":6.86,"pY":-0.07,"scY":0.91,"x":33.5}},{"z":7,"tweenEasing":0,"duration":3,"transform":{"y":34.45,"skX":19.26,"pX":0.03,"scX":1,"skY":19.26,"pY":-0.1,"scY":1.02,"x":40.15}},{"z":7,"tweenEasing":0,"duration":2,"transform":{"y":12.15,"skX":34.26,"pX":0.08,"scX":1,"skY":34.26,"pY":-0.1,"scY":1.02,"x":48.35}},{"z":7,"tweenEasing":0,"duration":3,"transform":{"y":56.3,"skX":0,"pX":0,"scX":1,"skY":0,"pY":0.03,"scY":0.87,"x":46}},{"z":7,"tweenEasing":0,"duration":3,"transform":{"y":56.33,"skX":0,"pX":0,"scX":1,"skY":0,"pY":0,"scY":1.21,"x":46}},{"z":7,"tweenEasing":0,"duration":4,"transform":{"y":56.33,"skX":0,"pX":0,"scX":1,"skY":0,"pY":0,"scY":1.21,"x":46}},{"z":7,"tweenEasing":0,"duration":5,"transform":{"y":56.33,"skX":0,"pX":0,"scX":1,"skY":0,"pY":0,"scY":1.21,"x":46}},{"z":7,"duration":1,"transform":{"y":56.33,"skX":0,"pX":0,"scX":1,"skY":0,"pY":0,"scY":1.21,"x":46}}],"offset":0},{"name":"head","scale":1,"frame":[{"z":8,"tweenEasing":0,"duration":6,"transform":{"y":24.18,"skX":0.01,"pX":0,"scX":1,"skY":0.01,"pY":0,"scY":1,"x":39.7}},{"z":8,"tweenEasing":0,"duration":4,"transform":{"y":24.88,"skX":17.44,"pX":0,"scX":1,"skY":17.44,"pY":0,"scY":1,"x":42.7}},{"z":8,"tweenEasing":0,"duration":5,"transform":{"y":26.73,"skX":32.43,"pX":0,"scX":1,"skY":32.43,"pY":0,"scY":1,"x":46.88}},{"z":8,"tweenEasing":0,"duration":4,"transform":{"y":27.45,"skX":37.63,"pX":0,"scX":1,"skY":37.63,"pY":0,"scY":1,"x":48.25}},{"z":8,"tweenEasing":0,"duration":3,"transform":{"y":33.75,"skX":-54.26,"pX":0,"scX":1,"skY":-54.26,"pY":0,"scY":1,"x":29.78}},{"z":8,"tweenEasing":0,"duration":3,"transform":{"y":19.58,"skX":0.01,"pX":0,"scX":1,"skY":0.01,"pY":0,"scY":1,"x":39.7}},{"z":8,"tweenEasing":0,"duration":3,"transform":{"y":19.58,"skX":0.01,"pX":0,"scX":1,"skY":0.01,"pY":0,"scY":1,"x":39.7}},{"z":8,"tweenEasing":0,"duration":2,"transform":{"y":21.73,"skX":0.01,"pX":0,"scX":1,"skY":0.01,"pY":0,"scY":1,"x":39.7}},{"z":8,"tweenEasing":0,"duration":3,"transform":{"y":27.23,"skX":-11.71,"pX":0,"scX":1,"skY":-11.71,"pY":0,"scY":1,"x":41.03}},{"z":8,"tweenEasing":0,"duration":3,"transform":{"y":-6.3,"skX":-8.13,"pX":0,"scX":1,"skY":-8.13,"pY":0,"scY":1,"x":33.05}},{"z":8,"tweenEasing":0,"duration":3,"transform":{"y":-18.07,"skX":-8.13,"pX":0,"scX":1,"skY":-8.13,"pY":0,"scY":1,"x":24.48}},{"z":8,"tweenEasing":0,"duration":3,"transform":{"y":19.1,"skX":6.87,"pX":0,"scX":1,"skY":6.87,"pY":0,"scY":1,"x":30.88}},{"z":8,"tweenEasing":0,"duration":3,"transform":{"y":15.2,"skX":6.87,"pX":0,"scX":1,"skY":6.87,"pY":0,"scY":1,"x":30.88}},{"z":8,"tweenEasing":0,"duration":3,"transform":{"y":14.23,"skX":-22.78,"pX":0,"scX":1,"skY":-22.78,"pY":0,"scY":1,"x":24.53}},{"z":8,"tweenEasing":0,"duration":3,"transform":{"y":14.23,"skX":-22.78,"pX":0,"scX":1,"skY":-22.78,"pY":0,"scY":1,"x":24.53}},{"z":8,"tweenEasing":0,"duration":3,"transform":{"y":14.23,"skX":-22.78,"pX":0,"scX":1,"skY":-22.78,"pY":0,"scY":1,"x":24.53}},{"z":8,"tweenEasing":0,"duration":3,"transform":{"y":14.23,"skX":-22.78,"pX":0,"scX":1,"skY":-22.78,"pY":0,"scY":1,"x":24.53}},{"z":8,"tweenEasing":0,"duration":3,"transform":{"y":14.23,"skX":-22.78,"pX":0,"scX":1,"skY":-22.78,"pY":0,"scY":1,"x":24.53}},{"z":8,"tweenEasing":0,"duration":3,"transform":{"y":14.23,"skX":-22.78,"pX":0,"scX":1,"skY":-22.78,"pY":0,"scY":1,"x":24.53}},{"z":8,"tweenEasing":0,"duration":3,"transform":{"y":14.23,"skX":-22.78,"pX":0,"scX":1,"skY":-22.78,"pY":0,"scY":1,"x":24.53}},{"z":8,"tweenEasing":0,"duration":3,"transform":{"y":14.23,"skX":-22.78,"pX":0,"scX":1,"skY":-22.78,"pY":0,"scY":1,"x":24.53}},{"z":8,"tweenEasing":0,"duration":3,"transform":{"y":15.6,"skX":-30.72,"pX":0,"scX":1,"skY":-30.72,"pY":0,"scY":1,"x":22.58}},{"z":8,"duration":1,"transform":{"y":15.18,"skX":-0.72,"pX":0,"scX":1,"skY":-0.72,"pY":0,"scY":1,"x":30.9}},{"z":8,"tweenEasing":0,"duration":6,"transform":{"y":15.18,"skX":-0.72,"pX":0,"scX":1,"skY":-0.72,"pY":0,"scY":1,"x":30.9}},{"z":8,"tweenEasing":0,"duration":6,"transform":{"y":16.52,"skX":17.75,"pX":0,"scX":1,"skY":17.75,"pY":0,"scY":1,"x":36.13}},{"z":8,"tweenEasing":0,"duration":7,"transform":{"y":16.52,"skX":17.75,"pX":0,"scX":1,"skY":17.75,"pY":0,"scY":1,"x":36.13}},{"z":8,"tweenEasing":0,"duration":6,"transform":{"y":16.52,"skX":17.75,"pX":0,"scX":1,"skY":17.75,"pY":0,"scY":1,"x":36.13}},{"z":8,"tweenEasing":0,"duration":6,"transform":{"y":16.52,"skX":17.75,"pX":0,"scX":1,"skY":17.75,"pY":0,"scY":1,"x":36.13}},{"z":8,"tweenEasing":0,"duration":6,"transform":{"y":16.52,"skX":17.75,"pX":0,"scX":1,"skY":17.75,"pY":0,"scY":1,"x":36.13}},{"z":8,"tweenEasing":0,"duration":7,"transform":{"y":16.52,"skX":17.75,"pX":0,"scX":1,"skY":17.75,"pY":0,"scY":1,"x":36.13}},{"z":8,"tweenEasing":0,"duration":6,"transform":{"y":16.52,"skX":17.75,"pX":0,"scX":1,"skY":17.75,"pY":0,"scY":1,"x":36.13}},{"z":8,"tweenEasing":0,"duration":7,"transform":{"y":16.52,"skX":17.75,"pX":0,"scX":1,"skY":17.75,"pY":0,"scY":1,"x":36.13}},{"z":8,"tweenEasing":0,"duration":3,"transform":{"y":15.18,"skX":-0.72,"pX":0,"scX":1,"skY":-0.72,"pY":0,"scY":1,"x":30.9}},{"z":8,"tweenEasing":0,"duration":3,"transform":{"y":15.18,"skX":9.52,"pX":0,"scX":1,"skY":9.52,"pY":0,"scY":1,"x":30.9}},{"z":8,"tweenEasing":0,"duration":3,"transform":{"y":20.43,"skX":-5.48,"pX":0,"scX":1,"skY":-5.48,"pY":0,"scY":1,"x":27.63}},{"z":8,"tweenEasing":0,"duration":3,"transform":{"y":3.05,"skX":11.7,"pX":0,"scX":1,"skY":11.7,"pY":0,"scY":1,"x":42.2}},{"z":8,"tweenEasing":0,"duration":2,"transform":{"y":-8.68,"skX":-18.29,"pX":0,"scX":1,"skY":-18.29,"pY":0,"scY":1,"x":50.13}},{"z":8,"tweenEasing":0,"duration":3,"transform":{"y":31.88,"skX":-14.99,"pX":0,"scX":1,"skY":-14.99,"pY":0,"scY":1,"x":37.58}},{"z":8,"tweenEasing":0,"duration":3,"transform":{"y":24.18,"skX":0.01,"pX":0,"scX":1,"skY":0.01,"pY":0,"scY":1,"x":39.7}},{"z":8,"tweenEasing":0,"duration":4,"transform":{"y":26.68,"skX":-14.99,"pX":0,"scX":1,"skY":-14.99,"pY":0,"scY":1,"x":35.55}},{"z":8,"tweenEasing":0,"duration":5,"transform":{"y":24.18,"skX":0.01,"pX":0,"scX":1,"skY":0.01,"pY":0,"scY":1,"x":39.7}},{"z":8,"duration":1,"transform":{"y":24.18,"skX":0.01,"pX":0,"scX":1,"skY":0.01,"pY":0,"scY":1,"x":39.7}}],"offset":0},{"name":"vidro_2","scale":1,"frame":[{"displayIndex":-1,"duration":73},{"z":9,"tweenEasing":0,"duration":6,"transform":{"y":20.08,"skX":0,"pX":0,"scX":1,"skY":0,"pY":0,"scY":1,"x":16.65}},{"z":9,"tweenEasing":0,"duration":6,"transform":{"y":10.13,"skX":48.47,"pX":0,"scX":1,"skY":48.47,"pY":-0.02,"scY":1,"x":25.7}},{"z":9,"tweenEasing":0,"duration":7,"transform":{"y":10.13,"skX":48.47,"pX":0,"scX":1,"skY":48.47,"pY":-0.02,"scY":1,"x":25.7}},{"z":9,"tweenEasing":0,"duration":6,"transform":{"y":10.13,"skX":48.47,"pX":0,"scX":1,"skY":48.47,"pY":-0.02,"scY":1,"x":25.7}},{"z":9,"tweenEasing":0,"duration":6,"transform":{"y":10.13,"skX":48.47,"pX":0,"scX":1,"skY":48.47,"pY":-0.02,"scY":1,"x":25.7}},{"z":9,"tweenEasing":0,"duration":6,"transform":{"y":10.13,"skX":48.47,"pX":0,"scX":1,"skY":48.47,"pY":-0.02,"scY":1,"x":25.7}},{"z":9,"tweenEasing":0,"duration":7,"transform":{"y":10.13,"skX":48.47,"pX":0,"scX":1,"skY":48.47,"pY":-0.02,"scY":1,"x":25.7}},{"z":9,"tweenEasing":0,"duration":6,"transform":{"y":10.13,"skX":48.47,"pX":0,"scX":1,"skY":48.47,"pY":-0.02,"scY":1,"x":25.7}},{"z":9,"tweenEasing":0,"duration":7,"transform":{"y":10.13,"skX":48.47,"pX":0,"scX":1,"skY":48.47,"pY":-0.02,"scY":1,"x":25.7}},{"z":9,"duration":1,"transform":{"y":20.08,"skX":0,"pX":0,"scX":1,"skY":0,"pY":0,"scY":1,"x":16.65}},{"displayIndex":-1,"duration":29}],"offset":0},{"name":"eye","scale":1,"frame":[{"z":10,"tweenEasing":0,"duration":6,"transform":{"y":7.45,"skX":1.25,"pX":0,"scX":1.01,"skY":-5.05,"pY":-0.02,"scY":1.44,"x":32.25}},{"z":10,"tweenEasing":0,"duration":4,"transform":{"y":6.75,"skX":18.68,"pX":-0.02,"scX":1.01,"skY":12.42,"pY":-0.02,"scY":1.44,"x":40.67}},{"z":10,"tweenEasing":0,"duration":5,"transform":{"y":8.7,"skX":33.68,"pX":-0.02,"scX":1.01,"skY":27.42,"pY":0,"scY":1.44,"x":49.63}},{"z":10,"tweenEasing":0,"duration":2,"transform":{"y":9.75,"skX":38.88,"pX":-0.07,"scX":1.01,"skY":32.61,"pY":0.03,"scY":1.44,"x":52.68}},{"z":10,"tweenEasing":0,"duration":2,"transform":{"y":13.53,"skX":-9.55,"pX":-0.05,"scX":1.01,"skY":-15.81,"pY":0.03,"scY":1.43,"x":27.2}},{"z":10,"tweenEasing":0,"duration":3,"transform":{"y":29.93,"skX":-53.02,"pX":-0.05,"scX":1.01,"skY":-59.28,"pY":0,"scY":1.44,"x":11.93}},{"z":10,"tweenEasing":0,"duration":3,"transform":{"y":2.85,"skX":1.25,"pX":0,"scX":1.01,"skY":-5.05,"pY":-0.05,"scY":1.44,"x":32.25}},{"z":10,"tweenEasing":0,"duration":3,"transform":{"y":2.85,"skX":1.25,"pX":0,"scX":1.01,"skY":-5.05,"pY":-0.05,"scY":1.44,"x":32.25}},{"z":10,"tweenEasing":0,"duration":2,"transform":{"y":5,"skX":1.25,"pX":0,"scX":1.01,"skY":-5.05,"pY":-0.05,"scY":1.44,"x":32.25}},{"z":10,"tweenEasing":0,"duration":3,"transform":{"y":12.35,"skX":-10.46,"pX":0.03,"scX":1.01,"skY":-16.76,"pY":-0.05,"scY":1.44,"x":30.33}},{"z":10,"tweenEasing":0,"duration":3,"transform":{"y":-21.82,"skX":-6.89,"pX":0,"scX":1.01,"skY":-13.19,"pY":0.03,"scY":1.44,"x":23.28}},{"z":10,"tweenEasing":0,"duration":3,"transform":{"y":-33.58,"skX":-6.89,"pX":-0.02,"scX":1.01,"skY":-13.19,"pY":0,"scY":1.44,"x":14.73}},{"z":10,"tweenEasing":0,"duration":3,"transform":{"y":1.6,"skX":8.11,"pX":-0.02,"scX":1.01,"skY":1.81,"pY":0.03,"scY":1.44,"x":25.48}},{"z":10,"tweenEasing":0,"duration":3,"transform":{"y":-2.3,"skX":8.11,"pX":-0.02,"scX":1.01,"skY":1.81,"pY":0,"scY":1.44,"x":25.48}},{"z":10,"tweenEasing":0,"duration":3,"transform":{"y":1.7,"skX":-21.54,"pX":0,"scX":1.01,"skY":-27.84,"pY":0,"scY":1.44,"x":11.18}},{"z":10,"tweenEasing":0,"duration":3,"transform":{"y":1.7,"skX":-21.54,"pX":0,"scX":1.01,"skY":-27.84,"pY":0,"scY":1.44,"x":11.18}},{"z":10,"tweenEasing":0,"duration":3,"transform":{"y":1.7,"skX":-21.54,"pX":0,"scX":1.01,"skY":-27.84,"pY":0,"scY":1.44,"x":11.18}},{"z":10,"tweenEasing":0,"duration":3,"transform":{"y":1.7,"skX":-21.54,"pX":0,"scX":1.01,"skY":-27.84,"pY":0,"scY":1.44,"x":11.18}},{"z":10,"tweenEasing":0,"duration":3,"transform":{"y":1.7,"skX":-21.54,"pX":0,"scX":1.01,"skY":-27.84,"pY":0,"scY":1.44,"x":11.18}},{"z":10,"tweenEasing":0,"duration":3,"transform":{"y":1.7,"skX":-21.54,"pX":0,"scX":1.01,"skY":-27.84,"pY":0,"scY":1.44,"x":11.18}},{"z":10,"tweenEasing":0,"duration":3,"transform":{"y":1.7,"skX":-21.54,"pX":0,"scX":1.01,"skY":-27.84,"pY":0,"scY":1.44,"x":11.18}},{"z":10,"tweenEasing":0,"duration":3,"transform":{"y":1.7,"skX":-21.54,"pX":0,"scX":1.01,"skY":-27.84,"pY":0,"scY":1.44,"x":11.18}},{"z":10,"tweenEasing":0,"duration":3,"transform":{"y":5,"skX":-29.47,"pX":-0.02,"scX":1.01,"skY":-35.77,"pY":-0.05,"scY":1.44,"x":7.63}},{"z":10,"duration":1,"transform":{"y":-1.47,"skX":0.53,"pX":0,"scX":1.01,"skY":-5.77,"pY":-0.05,"scY":1.44,"x":23.25}},{"z":10,"tweenEasing":0,"duration":6,"transform":{"y":-1.47,"skX":0.53,"pX":0,"scX":1.01,"skY":-5.77,"pY":-0.05,"scY":1.44,"x":23.25}},{"z":10,"tweenEasing":0,"duration":6,"transform":{"y":0.53,"skX":-154.51,"pX":0,"scX":-1.01,"skY":-160.81,"pY":-0.05,"scY":0.51,"x":33.17}},{"z":10,"tweenEasing":0,"duration":7,"transform":{"y":0.53,"skX":-154.51,"pX":0,"scX":-1.01,"skY":-160.81,"pY":-0.05,"scY":0.51,"x":33.17}},{"z":10,"tweenEasing":0,"duration":6,"transform":{"y":0.53,"skX":-154.51,"pX":0,"scX":-1.01,"skY":-160.81,"pY":-0.05,"scY":0.51,"x":33.17}},{"z":10,"tweenEasing":0,"duration":6,"transform":{"y":0.53,"skX":-154.51,"pX":0,"scX":-1.01,"skY":-160.81,"pY":-0.05,"scY":0.51,"x":33.17}},{"z":10,"tweenEasing":0,"duration":6,"transform":{"y":0.53,"skX":-154.51,"pX":0,"scX":-1.01,"skY":-160.81,"pY":-0.05,"scY":0.51,"x":33.17}},{"z":10,"tweenEasing":0,"duration":7,"transform":{"y":0.53,"skX":-154.51,"pX":0,"scX":-1.01,"skY":-160.81,"pY":-0.05,"scY":0.51,"x":33.17}},{"z":10,"tweenEasing":0,"duration":6,"transform":{"y":0.53,"skX":-154.51,"pX":0,"scX":-1.01,"skY":-160.81,"pY":-0.05,"scY":0.51,"x":33.17}},{"z":10,"tweenEasing":0,"duration":7,"transform":{"y":0.53,"skX":-154.51,"pX":0,"scX":-1.01,"skY":-160.81,"pY":-0.05,"scY":0.51,"x":33.17}},{"z":10,"tweenEasing":0,"duration":3,"transform":{"y":-1.47,"skX":0.53,"pX":0,"scX":1.01,"skY":-5.77,"pY":-0.05,"scY":1.44,"x":23.25}},{"z":10,"tweenEasing":0,"duration":3,"transform":{"y":-2.57,"skX":10.77,"pX":-0.02,"scX":1.01,"skY":4.47,"pY":-0.02,"scY":1.44,"x":26.33}},{"z":10,"tweenEasing":0,"duration":3,"transform":{"y":4.45,"skX":-4.23,"pX":-0.05,"scX":1.01,"skY":-10.53,"pY":-0.02,"scY":1.44,"x":18.6}},{"z":10,"tweenEasing":0,"duration":3,"transform":{"y":-14.85,"skX":12.96,"pX":-0.02,"scX":1.01,"skY":6.69,"pY":0,"scY":1.44,"x":38.28}},{"z":10,"tweenEasing":0,"duration":2,"transform":{"y":-22.22,"skX":-17.04,"pX":-0.02,"scX":1.01,"skY":-23.31,"pY":-0.02,"scY":1.44,"x":37.75}},{"z":10,"tweenEasing":0,"duration":3,"transform":{"y":17.63,"skX":-13.75,"pX":-0.02,"scX":1.01,"skY":-20.05,"pY":0,"scY":1.44,"x":26.08}},{"z":10,"tweenEasing":0,"duration":3,"transform":{"y":7.45,"skX":1.25,"pX":0,"scX":1.01,"skY":-5.05,"pY":-0.02,"scY":1.44,"x":32.25}},{"z":10,"tweenEasing":0,"duration":4,"transform":{"y":12.43,"skX":-13.75,"pX":-0.02,"scX":1.01,"skY":-20.05,"pY":0,"scY":1.44,"x":24.03}},{"z":10,"tweenEasing":0,"duration":5,"transform":{"y":7.45,"skX":1.25,"pX":0,"scX":1.01,"skY":-5.05,"pY":-0.02,"scY":1.44,"x":32.25}},{"z":10,"duration":1,"transform":{"y":7.45,"skX":1.25,"pX":0,"scX":1.01,"skY":-5.05,"pY":-0.02,"scY":1.44,"x":32.25}}],"offset":0},{"name":"viyi","scale":1,"frame":[{"z":11,"tweenEasing":0,"duration":6,"transform":{"y":-4.05,"skX":-0.81,"pX":0,"scX":1,"skY":1.29,"pY":0,"scY":1,"x":34.17}},{"z":11,"tweenEasing":0,"duration":4,"transform":{"y":-3.7,"skX":16.67,"pX":0,"scX":1,"skY":18.69,"pY":0.03,"scY":1,"x":45.93}},{"z":11,"tweenEasing":0,"duration":5,"transform":{"y":-0.05,"skX":31.67,"pX":0,"scX":1,"skY":33.69,"pY":0.03,"scY":1,"x":57.38}},{"z":11,"tweenEasing":0,"duration":2,"transform":{"y":1.73,"skX":36.86,"pX":0.03,"scX":1,"skY":38.88,"pY":0.05,"scY":1,"x":61.15}},{"z":11,"tweenEasing":0,"duration":2,"transform":{"y":5.1,"skX":-11.55,"pX":0,"scX":1,"skY":-9.55,"pY":0,"scY":1,"x":26.95}},{"z":11,"tweenEasing":0,"duration":3,"transform":{"y":21.68,"skX":-55.03,"pX":-0.02,"scX":1,"skY":-53.01,"pY":0,"scY":1,"x":3.65}},{"z":11,"tweenEasing":0,"duration":3,"transform":{"y":-8.65,"skX":-0.81,"pX":0,"scX":1,"skY":1.29,"pY":0,"scY":1,"x":34.17}},{"z":11,"tweenEasing":0,"duration":3,"transform":{"y":-8.65,"skX":-0.81,"pX":0,"scX":1,"skY":1.29,"pY":0,"scY":1,"x":34.17}},{"z":11,"tweenEasing":0,"duration":2,"transform":{"y":-6.5,"skX":-0.81,"pX":0,"scX":1,"skY":1.29,"pY":0,"scY":1,"x":34.17}},{"z":11,"tweenEasing":0,"duration":3,"transform":{"y":0.68,"skX":-12.52,"pX":0,"scX":1,"skY":-10.43,"pY":0,"scY":1,"x":29.9}},{"z":11,"tweenEasing":0,"duration":3,"transform":{"y":-33.42,"skX":-8.95,"pX":0,"scX":1,"skY":-6.85,"pY":0,"scY":1,"x":23.6}},{"z":11,"tweenEasing":0,"duration":3,"transform":{"y":-45.2,"skX":-8.95,"pX":0,"scX":1,"skY":-6.85,"pY":0,"scY":1,"x":15.03}},{"z":11,"tweenEasing":0,"duration":3,"transform":{"y":-9.55,"skX":6.05,"pX":0,"scX":1,"skY":8.15,"pY":0,"scY":1,"x":28.78}},{"z":11,"tweenEasing":0,"duration":3,"transform":{"y":-13.45,"skX":6.05,"pX":0,"scX":1,"skY":8.15,"pY":0,"scY":1,"x":28.78}},{"z":11,"tweenEasing":0,"duration":3,"transform":{"y":-7.55,"skX":-30.4,"pX":0.03,"scX":1,"skY":-28.3,"pY":-0.02,"scY":1,"x":6.38}},{"z":11,"tweenEasing":0,"duration":3,"transform":{"y":-7.55,"skX":-30.4,"pX":0.03,"scX":1,"skY":-28.3,"pY":-0.02,"scY":1,"x":6.38}},{"z":11,"tweenEasing":0,"duration":3,"transform":{"y":-7.55,"skX":-30.4,"pX":0.03,"scX":1,"skY":-28.3,"pY":-0.02,"scY":1,"x":6.38}},{"z":11,"tweenEasing":0,"duration":3,"transform":{"y":-7.55,"skX":-30.4,"pX":0.03,"scX":1,"skY":-28.3,"pY":-0.02,"scY":1,"x":6.38}},{"z":11,"tweenEasing":0,"duration":3,"transform":{"y":-7.55,"skX":-30.4,"pX":0.03,"scX":1,"skY":-28.3,"pY":-0.02,"scY":1,"x":6.38}},{"z":11,"tweenEasing":0,"duration":3,"transform":{"y":-7.55,"skX":-30.4,"pX":0.03,"scX":1,"skY":-28.3,"pY":-0.02,"scY":1,"x":6.38}},{"z":11,"tweenEasing":0,"duration":3,"transform":{"y":-7.55,"skX":-30.4,"pX":0.03,"scX":1,"skY":-28.3,"pY":-0.02,"scY":1,"x":6.38}},{"z":11,"tweenEasing":0,"duration":3,"transform":{"y":-7.55,"skX":-30.4,"pX":0.03,"scX":1,"skY":-28.3,"pY":-0.02,"scY":1,"x":6.38}},{"z":11,"tweenEasing":0,"duration":3,"transform":{"y":-3.47,"skX":-38.34,"pX":0.03,"scX":1,"skY":-36.24,"pY":0,"scY":1,"x":1.58}},{"z":11,"duration":1,"transform":{"y":-11.82,"skX":-8.34,"pX":0,"scX":1,"skY":-6.24,"pY":0,"scY":1,"x":22.25}},{"z":11,"tweenEasing":0,"duration":6,"transform":{"y":-11.82,"skX":-8.34,"pX":0,"scX":1,"skY":-6.24,"pY":0,"scY":1,"x":22.25}},{"z":11,"tweenEasing":0,"duration":6,"transform":{"y":-11.85,"skX":10.13,"pX":-0.02,"scX":1,"skY":12.23,"pY":0,"scY":1,"x":36.48}},{"z":11,"tweenEasing":0,"duration":7,"transform":{"y":-11.85,"skX":10.13,"pX":-0.02,"scX":1,"skY":12.23,"pY":0,"scY":1,"x":36.48}},{"z":11,"tweenEasing":0,"duration":6,"transform":{"y":-11.85,"skX":10.13,"pX":-0.02,"scX":1,"skY":12.23,"pY":0,"scY":1,"x":36.48}},{"z":11,"tweenEasing":0,"duration":6,"transform":{"y":-11.85,"skX":10.13,"pX":-0.02,"scX":1,"skY":12.23,"pY":0,"scY":1,"x":36.48}},{"z":11,"tweenEasing":0,"duration":6,"transform":{"y":-11.85,"skX":10.13,"pX":-0.02,"scX":1,"skY":12.23,"pY":0,"scY":1,"x":36.48}},{"z":11,"tweenEasing":0,"duration":7,"transform":{"y":-11.85,"skX":10.13,"pX":-0.02,"scX":1,"skY":12.23,"pY":0,"scY":1,"x":36.48}},{"z":11,"tweenEasing":0,"duration":6,"transform":{"y":-11.85,"skX":10.13,"pX":-0.02,"scX":1,"skY":12.23,"pY":0,"scY":1,"x":36.48}},{"z":11,"tweenEasing":0,"duration":7,"transform":{"y":-11.85,"skX":10.13,"pX":-0.02,"scX":1,"skY":12.23,"pY":0,"scY":1,"x":36.48}},{"z":11,"tweenEasing":0,"duration":3,"transform":{"y":-11.82,"skX":-8.34,"pX":0,"scX":1,"skY":-6.24,"pY":0,"scY":1,"x":22.25}},{"z":11,"tweenEasing":0,"duration":3,"transform":{"y":-12.92,"skX":1.9,"pX":0,"scX":1,"skY":4,"pY":0,"scY":1,"x":27.2}},{"z":11,"tweenEasing":0,"duration":3,"transform":{"y":-5.77,"skX":-13.1,"pX":0.03,"scX":1,"skY":-11,"pY":0,"scY":1,"x":16.77}},{"z":11,"tweenEasing":0,"duration":3,"transform":{"y":-25.3,"skX":6.69,"pX":0.03,"scX":1,"skY":8.71,"pY":0,"scY":1,"x":40.63}},{"z":11,"tweenEasing":0,"duration":2,"transform":{"y":-32.47,"skX":-23.31,"pX":0.03,"scX":1,"skY":-21.29,"pY":0.03,"scY":1,"x":34.58}},{"z":11,"tweenEasing":0,"duration":3,"transform":{"y":6.05,"skX":-15.81,"pX":0,"scX":1,"skY":-13.71,"pY":0,"scY":1,"x":24.95}},{"z":11,"tweenEasing":0,"duration":3,"transform":{"y":-4.05,"skX":-0.81,"pX":0,"scX":1,"skY":1.29,"pY":0,"scY":1,"x":34.17}},{"z":11,"tweenEasing":0,"duration":4,"transform":{"y":0.85,"skX":-15.81,"pX":0,"scX":1,"skY":-13.71,"pY":0,"scY":1,"x":22.9}},{"z":11,"tweenEasing":0,"duration":5,"transform":{"y":-4.05,"skX":-0.81,"pX":0,"scX":1,"skY":1.29,"pY":0,"scY":1,"x":34.17}},{"z":11,"duration":1,"transform":{"y":-4.05,"skX":-0.81,"pX":0,"scX":1,"skY":1.29,"pY":0,"scY":1,"x":34.17}}],"offset":0},{"name":"handLeft","scale":1,"frame":[{"z":12,"tweenEasing":0,"duration":6,"transform":{"y":26.85,"skX":14.81,"pX":0.03,"scX":1,"skY":14.81,"pY":-0.07,"scY":0.92,"x":45.7}},{"z":12,"tweenEasing":0,"duration":4,"transform":{"y":28.2,"skX":24.75,"pX":0.05,"scX":1,"skY":24.75,"pY":-0.1,"scY":0.92,"x":48.25}},{"z":12,"tweenEasing":0,"duration":5,"transform":{"y":31.38,"skX":39.75,"pX":0.05,"scX":1,"skY":39.75,"pY":-0.07,"scY":0.92,"x":51.38}},{"z":12,"tweenEasing":0,"duration":4,"transform":{"y":32.5,"skX":14.94,"pX":0.03,"scX":1,"skY":14.94,"pY":-0.1,"scY":0.92,"x":52.33}},{"z":12,"tweenEasing":0,"duration":3,"transform":{"y":31.33,"skX":-27.98,"pX":0.03,"scX":1,"skY":-27.98,"pY":-0.07,"scY":0.92,"x":35.8}},{"z":12,"tweenEasing":0,"duration":3,"transform":{"y":22.25,"skX":14.81,"pX":0.03,"scX":1,"skY":14.81,"pY":-0.1,"scY":0.92,"x":45.7}},{"z":12,"tweenEasing":0,"duration":3,"transform":{"y":22.25,"skX":14.81,"pX":0.03,"scX":1,"skY":14.81,"pY":-0.1,"scY":0.92,"x":45.7}},{"z":12,"tweenEasing":0,"duration":2,"transform":{"y":24.4,"skX":14.81,"pX":0.03,"scX":1,"skY":14.81,"pY":-0.07,"scY":0.92,"x":45.7}},{"z":12,"tweenEasing":0,"duration":3,"transform":{"y":28.63,"skX":3.09,"pX":0.03,"scX":1,"skY":3.1,"pY":-0.07,"scY":0.92,"x":47.45}},{"z":12,"tweenEasing":0,"duration":3,"transform":{"y":-4.47,"skX":6.67,"pX":0,"scX":1,"skY":6.67,"pY":-0.12,"scY":0.92,"x":39.35}},{"z":12,"tweenEasing":0,"duration":3,"transform":{"y":-19.73,"skX":66.67,"pX":0.03,"scX":1,"skY":66.67,"pY":-0.1,"scY":0.92,"x":30.83}},{"z":12,"tweenEasing":0,"duration":3,"transform":{"y":22.5,"skX":21.67,"pX":0.03,"scX":1,"skY":21.67,"pY":-0.12,"scY":0.92,"x":36.5}},{"z":12,"tweenEasing":0,"duration":3,"transform":{"y":18.6,"skX":21.67,"pX":0.03,"scX":1,"skY":21.67,"pY":-0.12,"scY":0.92,"x":36.5}},{"z":12,"tweenEasing":0,"duration":3,"transform":{"y":15.05,"skX":88.47,"pX":0.03,"scX":1,"skY":88.47,"pY":-0.12,"scY":1.09,"x":30.13}},{"z":12,"tweenEasing":0,"duration":3,"transform":{"y":15.05,"skX":103.47,"pX":0.05,"scX":1,"skY":103.47,"pY":-0.12,"scY":1.09,"x":30.13}},{"z":12,"tweenEasing":0,"duration":3,"transform":{"y":15.05,"skX":88.47,"pX":0.03,"scX":1,"skY":88.47,"pY":-0.12,"scY":1.09,"x":30.13}},{"z":12,"tweenEasing":0,"duration":3,"transform":{"y":15.05,"skX":103.47,"pX":0.05,"scX":1,"skY":103.47,"pY":-0.12,"scY":1.09,"x":30.13}},{"z":12,"tweenEasing":0,"duration":3,"transform":{"y":15.05,"skX":88.47,"pX":0.03,"scX":1,"skY":88.47,"pY":-0.12,"scY":1.09,"x":30.13}},{"z":12,"tweenEasing":0,"duration":3,"transform":{"y":15.05,"skX":103.47,"pX":0.05,"scX":1,"skY":103.47,"pY":-0.12,"scY":1.09,"x":30.13}},{"z":12,"tweenEasing":0,"duration":3,"transform":{"y":15.05,"skX":88.47,"pX":0.03,"scX":1,"skY":88.47,"pY":-0.12,"scY":1.09,"x":30.13}},{"z":12,"tweenEasing":0,"duration":3,"transform":{"y":15.05,"skX":103.47,"pX":0.05,"scX":1,"skY":103.47,"pY":-0.12,"scY":1.09,"x":30.13}},{"z":12,"tweenEasing":0,"duration":3,"transform":{"y":15.63,"skX":80.53,"pX":0,"scX":1,"skY":80.54,"pY":-0.12,"scY":1.09,"x":28.2}},{"z":12,"duration":1,"transform":{"y":18.02,"skX":110.53,"pX":0.05,"scX":1,"skY":110.54,"pY":-0.12,"scY":1.09,"x":35.78}},{"z":12,"tweenEasing":0,"duration":6,"transform":{"y":18.02,"skX":110.53,"pX":0.05,"scX":1,"skY":110.54,"pY":-0.12,"scY":1.09,"x":35.78}},{"z":12,"tweenEasing":0,"duration":6,"transform":{"y":20.75,"skX":159,"pX":0,"scX":1,"skY":159,"pY":-0.12,"scY":1.09,"x":39.85}},{"z":12,"tweenEasing":0,"duration":7,"transform":{"y":20.75,"skX":159,"pX":0,"scX":1,"skY":159,"pY":-0.12,"scY":1.09,"x":39.85}},{"z":12,"tweenEasing":0,"duration":6,"transform":{"y":20.75,"skX":159,"pX":0,"scX":1,"skY":159,"pY":-0.12,"scY":1.09,"x":39.85}},{"z":12,"tweenEasing":0,"duration":6,"transform":{"y":20.75,"skX":159,"pX":0,"scX":1,"skY":159,"pY":-0.12,"scY":1.09,"x":39.85}},{"z":12,"tweenEasing":0,"duration":6,"transform":{"y":20.75,"skX":159,"pX":0,"scX":1,"skY":159,"pY":-0.12,"scY":1.09,"x":39.85}},{"z":12,"tweenEasing":0,"duration":7,"transform":{"y":20.75,"skX":159,"pX":0,"scX":1,"skY":159,"pY":-0.12,"scY":1.09,"x":39.85}},{"z":12,"tweenEasing":0,"duration":6,"transform":{"y":20.75,"skX":159,"pX":0,"scX":1,"skY":159,"pY":-0.12,"scY":1.09,"x":39.85}},{"z":12,"tweenEasing":0,"duration":7,"transform":{"y":20.75,"skX":159,"pX":0,"scX":1,"skY":159,"pY":-0.12,"scY":1.09,"x":39.85}},{"z":12,"tweenEasing":0,"duration":3,"transform":{"y":18.02,"skX":110.53,"pX":0.05,"scX":1,"skY":110.54,"pY":-0.12,"scY":1.09,"x":35.78}},{"z":12,"tweenEasing":0,"duration":3,"transform":{"y":17.98,"skX":5.53,"pX":0.03,"scX":1,"skY":5.54,"pY":-0.12,"scY":1.09,"x":35.8}},{"z":12,"tweenEasing":0,"duration":3,"transform":{"y":21.85,"skX":-9.47,"pX":0.05,"scX":1,"skY":-9.46,"pY":-0.1,"scY":1.09,"x":33.08}},{"z":12,"tweenEasing":0,"duration":3,"transform":{"y":6.3,"skX":14.72,"pX":0.08,"scX":1,"skY":14.72,"pY":-0.1,"scY":1.03,"x":47.18}},{"z":12,"tweenEasing":0,"duration":2,"transform":{"y":-9.07,"skX":-0.28,"pX":0.08,"scX":1,"skY":-0.28,"pY":-0.05,"scY":1.03,"x":55.35}},{"z":12,"tweenEasing":0,"duration":3,"transform":{"y":32.9,"skX":-0.19,"pX":0.03,"scX":1,"skY":-0.19,"pY":-0.05,"scY":0.92,"x":44.08}},{"z":12,"tweenEasing":0,"duration":3,"transform":{"y":26.85,"skX":14.81,"pX":0.03,"scX":1,"skY":14.81,"pY":-0.07,"scY":0.92,"x":45.7}},{"z":12,"tweenEasing":0,"duration":4,"transform":{"y":27.75,"skX":29.81,"pX":0,"scX":1,"skY":29.81,"pY":-0.15,"scY":0.92,"x":42.05}},{"z":12,"tweenEasing":0,"duration":5,"transform":{"y":26.85,"skX":44.81,"pX":0,"scX":1,"skY":44.81,"pY":-0.1,"scY":0.92,"x":45.7}},{"z":12,"duration":1,"transform":{"y":26.85,"skX":14.81,"pX":0.03,"scX":1,"skY":14.81,"pY":-0.07,"scY":0.92,"x":45.7}}],"offset":0},{"name":"vidro","scale":1,"frame":[{"displayIndex":-1,"duration":69},{"z":16,"tweenEasing":0,"duration":3,"transform":{"y":22.43,"skX":48.94,"pX":0,"scX":1,"skY":0,"pY":0,"scY":0.67,"x":8.03}},{"z":16,"duration":1,"transform":{"y":16.93,"skX":0,"pX":0,"scX":1,"skY":0,"pY":-0.02,"scY":1,"x":16.13}},{"displayIndex":-1,"duration":87}],"offset":0}],"tweenEasing":null,"scale":1,"duration":160,"autoTween":0},{"fadeInTime":0,"loop":1,"name":"back","timeline":[{"name":"osnova","scale":1,"frame":[{"z":0,"duration":5,"transform":{"y":0.2,"skX":0,"pX":0,"scX":1,"skY":0,"pY":0,"scY":1,"x":-0.2}},{"displayIndex":-1,"duration":9}],"offset":0},{"name":"legRight","scale":1,"frame":[{"z":3,"tweenEasing":0,"duration":4,"transform":{"y":54.25,"skX":-8.03,"pX":0,"scX":1,"skY":-8.03,"pY":-0.05,"scY":1.16,"x":39.83}},{"z":3,"tweenEasing":0,"duration":3,"transform":{"y":54.2,"skX":-1.85,"pX":-0.05,"scX":1,"skY":-8.03,"pY":-0.05,"scY":1.16,"x":39.85}},{"z":3,"tweenEasing":0,"duration":3,"transform":{"y":28.83,"skX":46.2,"pX":0.05,"scX":1,"skY":46.2,"pY":-0.1,"scY":1.16,"x":21.8}},{"z":3,"tweenEasing":0,"duration":3,"transform":{"y":27.35,"skX":-10.33,"pX":-0.05,"scX":1,"skY":-16.51,"pY":-0.02,"scY":1.16,"x":19.3}},{"z":3,"duration":1,"transform":{"y":15.03,"skX":46.2,"pX":0.08,"scX":1,"skY":46.2,"pY":-0.1,"scY":1.16,"x":-10.75}}],"offset":0},{"name":"tail","scale":1,"frame":[{"z":4,"tweenEasing":0,"duration":4,"transform":{"y":37.38,"skX":-59.95,"pX":0,"scX":1,"skY":-59.95,"pY":0,"scY":1,"x":44.98}},{"z":4,"tweenEasing":0,"duration":3,"transform":{"y":38.73,"skX":-44.95,"pX":-0.02,"scX":1,"skY":-44.95,"pY":0,"scY":1,"x":47.15}},{"z":4,"tweenEasing":0,"duration":3,"transform":{"y":20.2,"skX":-50.72,"pX":0.03,"scX":1,"skY":-50.72,"pY":0,"scY":1,"x":38.88}},{"z":4,"tweenEasing":0,"duration":3,"transform":{"y":10.95,"skX":-53.43,"pX":-0.07,"scX":1,"skY":-53.43,"pY":0.03,"scY":1,"x":24.25}},{"z":4,"duration":1,"transform":{"y":6.4,"skX":-50.72,"pX":0,"scX":1,"skY":-50.72,"pY":0,"scY":1,"x":6.33}}],"offset":0},{"name":"handRight","scale":1,"frame":[{"z":5,"tweenEasing":0,"duration":4,"transform":{"y":24.5,"skX":-4.23,"pX":-0.05,"scX":1,"skY":-4.23,"pY":-0.02,"scY":1.17,"x":36.65}},{"z":5,"tweenEasing":0,"duration":3,"transform":{"y":24.13,"skX":10.77,"pX":-0.02,"scX":1,"skY":10.77,"pY":-0.02,"scY":1.17,"x":42.43}},{"z":5,"tweenEasing":0,"duration":3,"transform":{"y":6.13,"skX":5.01,"pX":0,"scX":1,"skY":5.01,"pY":0,"scY":1.17,"x":32.73}},{"z":5,"tweenEasing":0,"duration":3,"transform":{"y":-2.77,"skX":2.3,"pX":-0.05,"scX":1,"skY":2.29,"pY":-0.02,"scY":1.17,"x":17.43}},{"z":5,"duration":1,"transform":{"y":-7.67,"skX":5.01,"pX":0,"scX":1,"skY":5.01,"pY":0.03,"scY":1.17,"x":0.18}}],"offset":0},{"name":"body","scale":1,"frame":[{"z":6,"tweenEasing":0,"duration":4,"transform":{"y":42.78,"skX":-4.05,"pX":0,"scX":1,"skY":-4.05,"pY":0,"scY":0.93,"x":42.23}},{"z":6,"tweenEasing":0,"duration":3,"transform":{"y":43.23,"skX":10.95,"pX":0,"scX":1,"skY":10.95,"pY":0,"scY":0.93,"x":43.08}},{"z":6,"tweenEasing":0,"duration":3,"transform":{"y":25.05,"skX":5.19,"pX":0,"scX":1,"skY":5.19,"pY":0,"scY":0.93,"x":35.3}},{"z":6,"tweenEasing":0,"duration":3,"transform":{"y":16,"skX":2.47,"pX":0,"scX":1,"skY":2.47,"pY":0,"scY":0.93,"x":20.9}},{"z":6,"duration":1,"transform":{"y":11.25,"skX":5.19,"pX":0,"scX":1,"skY":5.19,"pY":0,"scY":0.93,"x":2.75}}],"offset":0},{"name":"legLeft","scale":1,"frame":[{"z":7,"tweenEasing":0,"duration":4,"transform":{"y":56.33,"skX":0,"pX":0,"scX":1,"skY":0,"pY":0,"scY":1.21,"x":46}},{"z":7,"tweenEasing":0,"duration":3,"transform":{"y":56.33,"skX":8.77,"pX":0,"scX":1,"skY":0,"pY":0,"scY":1.22,"x":46}},{"z":7,"tweenEasing":0,"duration":3,"transform":{"y":35.42,"skX":-35.76,"pX":-0.05,"scX":1,"skY":-35.76,"pY":-0.05,"scY":1.21,"x":48.28}},{"z":7,"tweenEasing":0,"duration":3,"transform":{"y":28.58,"skX":0.29,"pX":0,"scX":1,"skY":-8.48,"pY":0.03,"scY":1.22,"x":25.7}},{"z":7,"duration":1,"transform":{"y":21.63,"skX":-35.76,"pX":-0.02,"scX":1,"skY":-35.76,"pY":-0.05,"scY":1.21,"x":15.73}}],"offset":0},{"name":"head","scale":1,"frame":[{"z":8,"tweenEasing":0,"duration":4,"transform":{"y":24.18,"skX":0.01,"pX":0,"scX":1,"skY":0.01,"pY":0,"scY":1,"x":39.7}},{"z":8,"tweenEasing":0,"duration":3,"transform":{"y":24.6,"skX":15,"pX":0,"scX":1,"skY":15,"pY":0,"scY":1,"x":45.48}},{"z":8,"tweenEasing":0,"duration":3,"transform":{"y":6.33,"skX":-5.76,"pX":0,"scX":1,"skY":-5.76,"pY":0,"scY":1,"x":35.78}},{"z":8,"tweenEasing":0,"duration":3,"transform":{"y":-2.77,"skX":6.53,"pX":0,"scX":1,"skY":6.53,"pY":0,"scY":1,"x":20.53}},{"z":8,"duration":1,"transform":{"y":-7.47,"skX":-5.76,"pX":0,"scX":1,"skY":-5.76,"pY":0,"scY":1,"x":3.23}}],"offset":0},{"name":"eye","scale":1,"frame":[{"z":10,"tweenEasing":0,"duration":4,"transform":{"y":7.45,"skX":1.25,"pX":0,"scX":1.01,"skY":-5.05,"pY":-0.02,"scY":1.44,"x":32.25}},{"z":10,"tweenEasing":0,"duration":3,"transform":{"y":6.53,"skX":16.25,"pX":0,"scX":1.01,"skY":9.95,"pY":-0.02,"scY":1.44,"x":42.6}},{"z":10,"tweenEasing":0,"duration":3,"transform":{"y":-9.6,"skX":-4.51,"pX":0.03,"scX":1.01,"skY":-10.81,"pY":0,"scY":1.44,"x":26.68}},{"z":10,"tweenEasing":0,"duration":3,"transform":{"y":-20.25,"skX":7.77,"pX":0.03,"scX":1.01,"skY":1.47,"pY":0.03,"scY":1.44,"x":15}},{"z":10,"duration":1,"transform":{"y":-20.9,"skX":-4.51,"pX":0.03,"scX":1.01,"skY":-10.81,"pY":0,"scY":1.44,"x":1.27}}],"offset":0},{"name":"viyi","scale":1,"frame":[{"z":11,"tweenEasing":0,"duration":4,"transform":{"y":-4.05,"skX":-0.81,"pX":0,"scX":1,"skY":1.29,"pY":0,"scY":1,"x":34.17}},{"z":11,"tweenEasing":0,"duration":3,"transform":{"y":-4.07,"skX":14.19,"pX":0,"scX":1,"skY":16.29,"pY":-0.02,"scY":1,"x":47.43}},{"z":11,"tweenEasing":0,"duration":3,"transform":{"y":-21.2,"skX":-6.57,"pX":0,"scX":1,"skY":-4.47,"pY":0,"scY":1,"x":27.45}},{"z":11,"tweenEasing":0,"duration":3,"transform":{"y":-31.4,"skX":5.71,"pX":0,"scX":1,"skY":7.81,"pY":0,"scY":1,"x":18.23}},{"z":11,"duration":1,"transform":{"y":-32.5,"skX":-6.57,"pX":0,"scX":1,"skY":-4.47,"pY":0,"scY":1,"x":2.05}}],"offset":0},{"name":"handLeft","scale":1,"frame":[{"z":12,"tweenEasing":0,"duration":4,"transform":{"y":26.85,"skX":14.81,"pX":0.03,"scX":1,"skY":14.81,"pY":-0.07,"scY":0.92,"x":45.7}},{"z":12,"tweenEasing":0,"duration":3,"transform":{"y":28.73,"skX":29.81,"pX":0.05,"scX":1,"skY":29.81,"pY":-0.05,"scY":0.92,"x":50.58}},{"z":12,"tweenEasing":0,"duration":3,"transform":{"y":9.93,"skX":69.04,"pX":-0.07,"scX":1,"skY":69.04,"pY":-0.07,"scY":0.92,"x":41.3}},{"z":12,"tweenEasing":0,"duration":3,"transform":{"y":0.57,"skX":21.33,"pX":0.05,"scX":1,"skY":21.33,"pY":-0.1,"scY":0.92,"x":26.15}},{"z":12,"duration":1,"transform":{"y":-1.37,"skX":69.04,"pX":-0.07,"scX":1,"skY":69.04,"pY":-0.07,"scY":0.92,"x":15.9}}],"offset":0},{"name":"osnova_t","scale":1,"frame":[{"displayIndex":-1,"duration":5},{"z":15,"duration":9,"transform":{"y":0.2,"skX":0,"pX":0,"scX":1,"skY":0,"pY":0,"scY":1,"x":-0.2}}],"offset":0}],"tweenEasing":null,"scale":1,"duration":14,"autoTween":0},{"fadeInTime":0,"loop":1,"name":"over","timeline":[{"name":"osnova_t","scale":1,"frame":[{"z":15,"tweenEasing":0,"duration":3,"transform":{"y":0.2,"skX":0,"pX":0,"scX":1,"skY":0,"pY":0,"scY":1,"x":-0.2}},{"z":15,"tweenEasing":0,"duration":3,"transform":{"y":-3.8,"skX":0,"pX":0,"scX":1,"skY":0,"pY":0,"scY":1.08,"x":-0.2}},{"z":15,"tweenEasing":0,"duration":3,"transform":{"y":5.7,"skX":0,"pX":0,"scX":1.09,"skY":0,"pY":0,"scY":0.9,"x":-0.2}},{"z":15,"tweenEasing":0,"duration":3,"transform":{"y":-3.3,"skX":0,"pX":0,"scX":1,"skY":0,"pY":0,"scY":1.07,"x":-0.2}},{"z":15,"duration":1,"transform":{"y":0.2,"skX":0,"pX":0,"scX":1,"skY":0,"pY":0,"scY":1,"x":-0.2}}],"offset":0}],"tweenEasing":null,"scale":1,"duration":13,"autoTween":0}],"name":"decor","bone":[{"name":"cep","transform":{"y":13.13,"skX":0,"scX":1,"skY":0,"scY":1.06,"x":8.88}},{"name":"osnova_t","transform":{"y":0.2,"skX":0,"scX":1,"skY":0,"scY":1,"x":-0.2}},{"name":"osnova","transform":{"y":0.2,"skX":0,"scX":1,"skY":0,"scY":1,"x":-0.2}},{"name":"legRight","transform":{"y":3.05,"skX":0,"scX":-1,"skY":0,"scY":1,"x":10.98}},{"name":"tail","transform":{"y":-13.35,"skX":60,"scX":-1,"skY":60,"scY":1,"x":2.58}},{"name":"handRight","transform":{"y":-29.3,"skX":-10.81,"scX":-1,"skY":-10.81,"scY":1.17,"x":11.18}},{"name":"body","transform":{"y":-7.95,"skX":4.19,"scX":-1,"skY":4.19,"scY":0.93,"x":5.35}},{"name":"legLeft","transform":{"y":4.3,"skX":0,"scX":-1,"skY":0,"scY":1,"x":0.73}},{"name":"head","transform":{"y":-26.55,"skX":-0.02,"scX":-1,"skY":-0.02,"scY":1,"x":7.88}},{"name":"eye","transform":{"y":-43.27,"skX":-1.26,"scX":-1.02,"skY":5.19,"scY":1.44,"x":15.33}},{"name":"viyi","transform":{"y":-54.77,"skX":0.98,"scX":-1,"skY":-1.4,"scY":1,"x":13.43}},{"name":"handLeft","transform":{"y":-23.9,"skX":-29.8,"scX":-1,"skY":-29.8,"scY":0.92,"x":1.9}},{"name":"coin","transform":{"y":32.7,"skX":0,"scX":1,"skY":0,"scY":1,"x":23.83}},{"name":"oslin","transform":{"y":33.35,"skX":-45,"scX":0.36,"skY":-45,"scY":0.36,"x":24.45}},{"name":"vidro_2","transform":{"y":20.08,"skX":0,"scX":1,"skY":0,"scY":1,"x":16.65}},{"name":"vidro","transform":{"y":22.43,"skX":48.94,"scX":1,"skY":0,"scY":0.67,"x":8.03}}],"skin":[{"slot":[{"display":[{"transform":{"y":11.6,"skX":0,"pX":0.8,"scX":1,"skY":0,"pY":23.2,"scY":1,"x":0},"name":"cep","type":"image"}],"z":1,"name":"cep","parent":"cep"},{"display":[{"transform":{"y":0,"skX":0,"pX":42.25,"scX":1,"skY":0,"pY":59.25,"scY":1,"x":0},"name":"well_y","type":"image"}],"z":15,"name":"osnova_t","parent":"osnova_t"},{"display":[{"transform":{"y":0,"skX":0,"pX":42.25,"scX":1,"skY":0,"pY":59.25,"scY":1,"x":0},"name":"well_y","type":"image"}],"z":0,"name":"osnova","parent":"osnova"},{"display":[{"transform":{"y":-13.75,"skX":0,"pX":5.25,"scX":1,"skY":0,"pY":0,"scY":1,"x":0},"name":"legRight","type":"image"}],"z":3,"name":"legRight","parent":"legRight"},{"display":[{"transform":{"y":2.75,"skX":0,"pX":0,"scX":1,"skY":0,"pY":4.75,"scY":1,"x":-2.8},"name":"tail","type":"image"}],"z":4,"name":"tail","parent":"tail"},{"display":[{"transform":{"y":-1.67,"skX":0,"pX":4.5,"scX":1,"skY":0,"pY":0,"scY":1,"x":-2.25},"name":"handRight","type":"image"}],"z":5,"name":"handRight","parent":"handRight"},{"display":[{"transform":{"y":0,"skX":0,"pX":8.23,"scX":1,"skY":0,"pY":24.6,"scY":1,"x":0},"name":"body","type":"image"}],"z":6,"name":"body","parent":"body"},{"display":[{"transform":{"y":-15,"skX":0,"pX":5,"scX":1,"skY":0,"pY":0,"scY":1,"x":0},"name":"legLeft","type":"image"}],"z":7,"name":"legLeft","parent":"legLeft"},{"display":[{"transform":{"y":0,"skX":0,"pX":18.05,"scX":1,"skY":0,"pY":45.6,"scY":1,"x":0},"name":"head","type":"image"}],"z":8,"name":"head","parent":"head"},{"display":[{"transform":{"y":2.17,"skX":0,"pX":7.08,"scX":1,"skY":0,"pY":3.83,"scY":1,"x":-0.07},"name":"eyes","type":"image"}],"z":10,"name":"eye","parent":"eye"},{"display":[{"transform":{"y":-0.02,"skX":0,"pX":13.28,"scX":1,"skY":0,"pY":4.65,"scY":1,"x":0.03},"name":"viyi","type":"image"}],"z":11,"name":"viyi","parent":"viyi"},{"display":[{"transform":{"y":-3.07,"skX":0,"pX":5,"scX":1,"skY":0,"pY":0,"scY":1,"x":2.75},"name":"handLeft","type":"image"}],"z":12,"name":"handLeft","parent":"handLeft"},{"display":[{"transform":{"y":1.53,"skX":0,"pX":3.95,"scX":1,"skY":0,"pY":5.48,"scY":1,"x":0},"name":"coin","type":"image"}],"z":13,"name":"coin","parent":"coin"},{"display":[{"transform":{"y":20.35,"skX":0,"pX":22.5,"scX":1,"skY":0,"pY":40.5,"scY":1,"x":0.05},"name":"stone","type":"image"}],"z":2,"name":"oslin","parent":"oslin"},{"display":[{"transform":{"y":6.78,"skX":0,"pX":6.43,"scX":1,"skY":0,"pY":13.55,"scY":1,"x":0},"name":"vidro_2","type":"image"}],"z":9,"name":"vidro_2","parent":"vidro_2"},{"display":[{"transform":{"y":10.6,"skX":0,"pX":6.43,"scX":1,"skY":0,"pY":17.15,"scY":1,"x":0},"name":"vidro","type":"image"}],"z":16,"name":"vidro","parent":"vidro"}],"name":"default"}]}],"name":"well_yellow","frameRate":30,"version":2.3}