{"name":"cat_queue","SubTexture":[{"x":309,"name":"right_leg/legRight","y":142,"width":11,"height":15},{"x":338,"name":"tails/tail","y":153,"width":17,"height":10},{"x":280,"name":"right_hand/handRight","y":70,"width":9,"height":17},{"x":461,"name":"bodys/body","y":127,"width":17,"height":25},{"x":435,"name":"bodys/sharf","y":127,"width":13,"height":20},{"x":133,"name":"left_leg/legLeft","y":170,"width":10,"height":15},{"x":278,"name":"left_hand/handLeft","y":89,"width":11,"height":17},{"x":387,"name":"heads/head","y":47,"width":35,"height":45},{"x":290,"name":"heads/okuli_1","y":124,"width":31,"height":16},{"x":0,"name":"heads/bant","y":92,"width":30,"height":31},{"x":92,"name":"shmot/nota","y":0,"width":112,"height":33},{"x":61,"name":"shmot/gammm","y":173,"width":9,"height":10},{"x":504,"name":"shmot/penc_3","y":32,"width":4,"height":34},{"x":64,"name":"shmot/lustr","y":92,"width":16,"height":41},{"x":286,"name":"yaz","y":34,"width":4,"height":6},{"x":233,"name":"shmot/bloknot","y":171,"width":10,"height":13},{"x":498,"name":"shmot/player","y":0,"width":9,"height":30},{"x":245,"name":"shmot/iriss","y":171,"width":11,"height":8},{"x":358,"name":"shmot/kn_2","y":126,"width":13,"height":21},{"x":210,"name":"shmot/cup","y":167,"width":21,"height":15},{"x":322,"name":"shmot/gumki","y":172,"width":11,"height":8},{"x":165,"name":"shmot/cam","y":115,"width":33,"height":26},{"x":0,"name":"blik","y":0,"width":90,"height":90},{"x":280,"name":"shmot/penc_2","y":34,"width":4,"height":34},{"x":143,"name":"shmot/grebin","y":160,"width":18,"height":8},{"x":30,"name":"clock","y":172,"width":14,"height":8},{"x":91,"name":"shmot/glas","y":165,"width":28,"height":8},{"x":323,"name":"shmot/mic","y":101,"width":14,"height":27},{"x":240,"name":"shmot/flower","y":81,"width":36,"height":31},{"x":341,"name":"shmot/vuhi","y":0,"width":44,"height":44},{"x":378,"name":"shmot/iris","y":54,"width":7,"height":6},{"x":150,"name":"shmot/kn_1","y":120,"width":13,"height":21},{"x":378,"name":"shmot/gumka","y":46,"width":7,"height":6},{"x":121,"name":"shmot/gummb","y":119,"width":27,"height":27},{"x":292,"name":"__dbTextures/cat/clock_2006","y":0,"width":47,"height":42},{"x":121,"name":"shmot/morda","y":82,"width":29,"height":35},{"x":498,"name":"shmot/penc","y":32,"width":4,"height":34},{"x":121,"name":"shmot/busina","y":148,"width":20,"height":20},{"x":92,"name":"pack","y":82,"width":27,"height":39},{"x":92,"name":"shmot/pen","y":150,"width":17,"height":13},{"x":206,"name":"shmot/xvilki","y":0,"width":84,"height":32},{"x":91,"name":"shmot/latka","y":175,"width":9,"height":9},{"x":450,"name":"shmot/phone","y":168,"width":9,"height":16},{"x":238,"name":"shmot/sumka","y":147,"width":19,"height":22},{"x":309,"name":"left_leg_b/legLeft_b","y":159,"width":11,"height":15},{"x":426,"name":"right_leg_b/legRight_b","y":166,"width":10,"height":15},{"x":373,"name":"left_hand_b/handLeft_b","y":131,"width":9,"height":17},{"x":385,"name":"bodys_b/body_b","y":127,"width":17,"height":25},{"x":19,"name":"right_hand_b/handRight_b","y":125,"width":10,"height":17},{"x":461,"name":"heads_b/head_b","y":47,"width":35,"height":45},{"x":31,"name":"bodys/body_bl","y":125,"width":17,"height":25},{"x":339,"name":"bodys_b/body_b_bl","y":126,"width":17,"height":25},{"x":203,"name":"heads/head_bl","y":81,"width":35,"height":45},{"x":387,"name":"heads_b/head_b_bl","y":0,"width":35,"height":45},{"x":373,"name":"left_hand/handLeft_bl","y":93,"width":11,"height":17},{"x":404,"name":"left_hand_b/handLeft_b_bl","y":146,"width":9,"height":17},{"x":145,"name":"left_leg/legLeft_bl","y":170,"width":10,"height":15},{"x":259,"name":"left_leg_b/legLeft_b_bl","y":147,"width":11,"height":15},{"x":450,"name":"right_hand/handRight_bl","y":94,"width":9,"height":17},{"x":373,"name":"right_hand_b/handRight_b_bl","y":112,"width":10,"height":17},{"x":435,"name":"right_leg/legRight_bl","y":149,"width":11,"height":15},{"x":198,"name":"right_leg_b/legRight_b_bl","y":167,"width":10,"height":15},{"x":415,"name":"tails/tail_bl","y":154,"width":17,"height":10},{"x":82,"name":"eye/lid_l_blue","y":118,"width":8,"height":11},{"x":322,"name":"eye/lid_r_blue","y":158,"width":14,"height":12},{"x":111,"name":"eye/lid_l_black","y":136,"width":8,"height":11},{"x":272,"name":"eye/lid_r_black","y":162,"width":14,"height":12},{"x":498,"name":"eye/eye_l_blue","y":68,"width":3,"height":5},{"x":286,"name":"eye/eye_l_brown","y":56,"width":3,"height":5},{"x":286,"name":"eye/eye_l_green","y":49,"width":3,"height":5},{"x":286,"name":"eye/eye_l_grey","y":63,"width":3,"height":5},{"x":493,"name":"bodys/body_gr","y":121,"width":17,"height":25},{"x":290,"name":"bodys/body_or","y":142,"width":17,"height":25},{"x":92,"name":"bodys/body_pk","y":123,"width":17,"height":25},{"x":219,"name":"bodys_b/body_b_gr","y":128,"width":17,"height":25},{"x":163,"name":"bodys_b/body_b_or","y":143,"width":17,"height":25},{"x":200,"name":"bodys_b/body_b_pk","y":128,"width":17,"height":25},{"x":243,"name":"heads/head_gr","y":34,"width":35,"height":45},{"x":424,"name":"heads/head_or","y":47,"width":35,"height":45},{"x":341,"name":"heads/head_pk","y":46,"width":35,"height":45},{"x":92,"name":"heads_b/head_b_gr","y":35,"width":35,"height":45},{"x":206,"name":"heads_b/head_b_or","y":34,"width":35,"height":45},{"x":424,"name":"heads_b/head_b_pk","y":0,"width":35,"height":45},{"x":328,"name":"left_hand/handLeft_gr","y":82,"width":11,"height":17},{"x":152,"name":"left_hand/handLeft_or","y":101,"width":11,"height":17},{"x":152,"name":"left_hand/handLeft_pk","y":82,"width":11,"height":17},{"x":50,"name":"left_hand_b/handLeft_b_gr","y":144,"width":9,"height":17},{"x":403,"name":"left_hand_b/handLeft_b_or","y":165,"width":9,"height":17},{"x":450,"name":"left_hand_b/handLeft_b_pk","y":113,"width":9,"height":17},{"x":364,"name":"left_leg/legLeft_gr","y":167,"width":10,"height":15},{"x":169,"name":"left_leg/legLeft_or","y":170,"width":10,"height":15},{"x":438,"name":"right_leg_b/legRight_b_br","y":168,"width":10,"height":15},{"x":288,"name":"left_leg/legLeft_pk","y":169,"width":10,"height":15},{"x":480,"name":"left_leg_b/legLeft_b_gr","y":146,"width":11,"height":15},{"x":338,"name":"left_leg_b/legLeft_b_or","y":165,"width":11,"height":15},{"x":150,"name":"left_leg_b/legLeft_b_br","y":143,"width":11,"height":15},{"x":259,"name":"left_leg_b/legLeft_b_pk","y":164,"width":11,"height":15},{"x":81,"name":"right_hand/handRight_gr","y":144,"width":9,"height":17},{"x":19,"name":"right_hand/handRight_or","y":144,"width":9,"height":17},{"x":80,"name":"right_hand/handRight_pk","y":163,"width":9,"height":17},{"x":404,"name":"right_hand_b/handRight_b_gr","y":127,"width":10,"height":17},{"x":480,"name":"right_hand_b/handRight_b_or","y":127,"width":10,"height":17},{"x":50,"name":"right_hand_b/handRight_b_pk","y":125,"width":10,"height":17},{"x":358,"name":"right_leg/legRight_gr","y":149,"width":11,"height":15},{"x":0,"name":"right_leg/legRight_or","y":164,"width":11,"height":15},{"x":480,"name":"right_leg/legRight_pk","y":163,"width":11,"height":15},{"x":157,"name":"right_leg_b/legRight_b_gr","y":170,"width":10,"height":15},{"x":414,"name":"right_leg_b/legRight_b_or","y":166,"width":10,"height":15},{"x":493,"name":"right_leg_b/legRight_b_pk","y":167,"width":10,"height":15},{"x":217,"name":"tails/tail_gr","y":155,"width":17,"height":10},{"x":0,"name":"tails/tail_or","y":152,"width":17,"height":10},{"x":198,"name":"tails/tail_pk","y":155,"width":17,"height":10},{"x":416,"name":"bodys/body_wh","y":127,"width":17,"height":25},{"x":0,"name":"bodys_b/body_b_wh","y":125,"width":17,"height":25},{"x":129,"name":"heads/head_wh","y":35,"width":35,"height":45},{"x":30,"name":"shmot/necklace","y":152,"width":18,"height":18},{"x":493,"name":"shmot/cepka","y":148,"width":17,"height":17},{"x":272,"name":"shmot/galstuk","y":127,"width":16,"height":19},{"x":166,"name":"heads_b/head_b_wh","y":35,"width":35,"height":45},{"x":328,"name":"left_hand/handLeft_wh","y":63,"width":11,"height":17},{"x":450,"name":"left_hand_b/handLeft_b_wh","y":132,"width":9,"height":17},{"x":181,"name":"left_leg/legLeft_wh","y":171,"width":10,"height":15},{"x":448,"name":"left_leg_b/legLeft_b_wh","y":151,"width":11,"height":15},{"x":384,"name":"right_hand/handRight_wh","y":166,"width":9,"height":17},{"x":278,"name":"right_hand_b/handRight_b_wh","y":108,"width":10,"height":17},{"x":371,"name":"right_leg/legRight_wh","y":150,"width":11,"height":15},{"x":461,"name":"right_leg_b/legRight_b_wh","y":166,"width":10,"height":15},{"x":384,"name":"tails/tail_wh","y":154,"width":17,"height":10},{"x":111,"name":"eye/lid_l_green","y":149,"width":8,"height":11},{"x":182,"name":"eye/lid_r_green","y":143,"width":14,"height":12},{"x":82,"name":"eye/lid_l_brown","y":105,"width":8,"height":11},{"x":62,"name":"bodys/body_br","y":135,"width":17,"height":25},{"x":493,"name":"bodys_b/body_b_br","y":94,"width":17,"height":25},{"x":328,"name":"left_hand/handLeft_br","y":44,"width":11,"height":17},{"x":19,"name":"right_hand/handRight_br","y":163,"width":9,"height":17},{"x":498,"name":"right_hand_b/handRight_b_br","y":75,"width":11,"height":17},{"x":461,"name":"tails/tail_br","y":154,"width":17,"height":10},{"x":461,"name":"bant_1","y":94,"width":30,"height":31},{"x":341,"name":"bant_2","y":93,"width":30,"height":31},{"x":240,"name":"bant_3","y":114,"width":30,"height":31},{"x":32,"name":"bant_4","y":92,"width":30,"height":31},{"x":165,"name":"bant_5","y":82,"width":30,"height":31},{"x":291,"name":"bant_6","y":91,"width":30,"height":31},{"x":418,"name":"bant_7","y":94,"width":30,"height":31},{"x":386,"name":"bant_8","y":94,"width":30,"height":31},{"x":50,"name":"left_hand_b/handLeft_b_br","y":163,"width":9,"height":17},{"x":121,"name":"left_leg/legLeft_br","y":170,"width":10,"height":15},{"x":351,"name":"right_leg/legRight_br","y":166,"width":11,"height":15},{"x":182,"name":"eye/lid_r_brown","y":157,"width":14,"height":12},{"x":111,"name":"eye/lid_l_white","y":123,"width":8,"height":11},{"x":272,"name":"eye/lid_r_white","y":148,"width":14,"height":12},{"x":291,"name":"heads/head_br","y":44,"width":35,"height":45},{"x":461,"name":"heads_b/head_b_br","y":0,"width":35,"height":45},{"x":82,"name":"eye/lid_l_orange","y":92,"width":8,"height":11},{"x":323,"name":"eye/lid_r_orange","y":130,"width":14,"height":12},{"x":82,"name":"eye/lid_l_pink","y":131,"width":8,"height":11},{"x":322,"name":"eye/lid_r_pink","y":144,"width":14,"height":12},{"x":286,"name":"eye/eye_r","y":42,"width":3,"height":5},{"x":378,"name":"eye/eye_l","y":62,"width":3,"height":5},{"x":503,"name":"eye/lips","y":68,"width":6,"height":1},{"x":61,"name":"Symbol 1","y":162,"width":17,"height":9}],"imagePath":"texture.png"}