{"imagePath":"texture.png","SubTexture":[{"x":0,"height":107,"y":0,"name":"molbert","width":72},{"x":122,"height":17,"y":0,"name":"penzl","width":2},{"x":111,"height":17,"y":90,"name":"handLeft_b","width":9},{"x":111,"height":15,"y":73,"name":"leg_lb","width":11},{"x":93,"height":15,"y":102,"name":"legRight_b","width":10},{"x":74,"height":25,"y":102,"name":"body_b","width":17},{"x":111,"height":17,"y":54,"name":"handRight_b","width":10},{"x":0,"height":10,"y":109,"name":"tail","width":17},{"x":74,"height":46,"y":54,"name":"head_b","width":35},{"x":74,"height":52,"y":0,"name":"im_1","width":46}],"name":"easel_red"}